Workbook

Sheet Cleaned_IMDB_Movies
A1: color | B1: director_name | C1: num_critic_for_reviews | D1: duration | E1: director_facebook_likes | F1: actor_3_facebook_likes | G1: actor_2_name | H1: actor_1_facebook_likes | I1: gross | J1: genres | K1: actor_1_name | L1: movie_title | M1: num_voted_users | N1: cast_total_facebook_likes | O1: actor_3_name | P1: facenumber_in_poster | Q1: plot_keywords | R1: movie_imdb_link | S1: num_user_for_reviews | T1: language | U1: country | V1: content_rating | W1: budget | X1: title_year | Y1: actor_2_facebook_likes | Z1: imdb_score | AA1: aspect_ratio | AB1: movie_facebook_likes
A2: Color | C2: 12 | D2: 7 | F2: 3 | G2: John Sparkes | H2: 45 | J2: Animation|Comedy|Family | K2: Justin Fletcher | L2: Shaun the Sheep | M2: 7968 | N2: 55 | O2: Kate Harbour | P2: 0 | Q2: farmer|mischief|no dialog|sheep|sheepdog | R2: http://www.imdb.com/title/tt0983983/?ref_=fn_tt_tt_1 | S2: 12 | T2: English | U2: UK | V2: TV-G | Y2: 7 | Z2: 8.3 | AB2: 834
A3: Color | B3: Jane Clark | C3: 110 | D3: 7 | E3: 23 | F3: 51 | G3: Traci Dinwiddie | H3: 344 | J3: Romance|Short | K3: Necar Zadegan | L3: The Touch | M3: 118 | N3: 726 | O3: Elea Oberon | P3: 0 | Q3: lesbian|paris france|period piece|poem|poetess | R3: http://www.imdb.com/title/tt1128219/?ref_=fn_tt_tt_1 | S3: 156 | T3: English | U3: USA | V3: Unrated | W3: 13000 | X3: 2007 | Y3: 281 | Z3: 5.2 | AA3: 1.85 | AB3: 30
A4: Color | C4: 38 | D4: 11 | F4: 0 | G4: Seth Green | H4: 11 | J4: Animation|Comedy | K4: Matthew Senreich | L4: Robot Chicken | M4: 32923 | N4: 11 | O4: Breckin Meyer | P4: 0 | Q4: celebrity|robot|satire|sketch comedy|stop motion animation | R4: http://www.imdb.com/title/tt0437745/?ref_=fn_tt_tt_1 | S4: 75 | T4: English | U4: USA | V4: TV-MA | Y4: 0 | Z4: 7.8 | AA4: 1.33 | AB4: 1000
A5: Color | B5: Clark Baker | C5: 1 | D5: 14 | E5: 0 | F5: 37 | G5: Alan Pietruszewski | H5: 134 | J5: Horror|Sci-Fi|Short|Thriller | K5: Taylor Pigeon | L5: Vessel | M5: 292 | N5: 315 | O5: Whit Spurgeon | P5: 1 | Q5: alien|flight attendant|monster|pilot|tentacle | R5: http://www.imdb.com/title/tt2164708/?ref_=fn_tt_tt_1 | S5: 3 | T5: English | U5: USA | V5: Unrated | X5: 2012 | Y5: 93 | Z5: 6.2 | AB5: 14
A6: Color | B6: Robert Greenwald | C6: 56 | D6: 20 | E6: 21 | F6: 0 | G6: Jon Hunter | H6: 0 | J6: Documentary | K6: Lee Scott | L6: Wal-Mart: The High Cost of Low Price | M6: 4120 | N6: 0 | O6: Matt Hunter | P6: 0 | Q6: greed|pollution|slave labor|truth|wal mart | R6: http://www.imdb.com/title/tt0473107/?ref_=fn_tt_tt_1 | S6: 70 | T6: English | U6: USA | V6: Not Rated | W6: 1500000 | X6: 2005 | Y6: 0 | Z6: 6.8 | AA6: 1.85 | AB6: 0
A7: Color | C7: 8 | D7: 22 | F7: 402 | G7: Oliver Hudson | H7: 732 | J7: Comedy|Romance | K7: Bianca Kajlich | L7: Rules of Engagement | M7: 26404 | N7: 2064 | O7: Adhir Kalyan | P7: 3 | Q7: fiance|fiancee|magazine editor|naivety|womanizer | R7: http://www.imdb.com/title/tt0790772/?ref_=fn_tt_tt_1 | S7: 41 | T7: English | U7: USA | V7: TV-PG | Y7: 607 | Z7: 7.3 | AA7: 1.78 | AB7: 0
A8: Color | C8: 8 | D8: 22 | F8: 344 | G8: Amy Sedaris | H8: 459 | J8: Comedy | K8: Stephen Colbert | L8: Strangers with Candy | M8: 4181 | N8: 1359 | O8: Maria Thayer | P8: 3 | Q8: alternative comedy|female protagonist|high school|social satire|three word title | R8: http://www.imdb.com/title/tt0194624/?ref_=fn_tt_tt_1 | S8: 62 | T8: English | U8: USA | V8: TV-14 | Y8: 396 | Z8: 8.1 | AA8: 1.33 | AB8: 558
A9: Color | C9: 11 | D9: 22 | F9: 6 | G9: Ron Lynch | H9: 59 | J9: Animation|Comedy|Drama | K9: Brendon Small | L9: Home Movies | M9: 7458 | N9: 81 | O9: Melissa Bardin Galsky | P9: 0 | Q9: coach|friend|school|series|tv series | R9: http://www.imdb.com/title/tt0197159/?ref_=fn_tt_tt_1 | S9: 82 | T9: English | U9: USA | V9: TV-PG | Y9: 11 | Z9: 8.2 | AA9: 1.33 | AB9: 526
A10: Color | C10: 20 | D10: 22 | F10: 271 | G10: Soleil Moon Frye | H10: 870 | J10: Comedy|Family|Fantasy | K10: Nate Richert | L10: Sabrina, the Teenage Witch | M10: 24420 | N10: 2433 | O10: Caroline Rhea | P10: 1 | Q10: female protagonist|hereditary gift of witchcraft|magic|supernatural|witch | R10: http://www.imdb.com/title/tt0115341/?ref_=fn_tt_tt_1 | S10: 94 | T10: English | U10: USA | V10: TV-G | W10: 3000000 | Y10: 558 | Z10: 6.6 | AA10: 1.33 | AB10: 990
A11: Color | C11: 26 | D11: 22 | F11: 676 | G11: Noureen DeWulf | H11: 883 | J11: Comedy|Romance | K11: Barry Corbin | L11: Anger Management | M11: 26992 | N11: 4115 | O11: Brian Austin Green | P11: 1 | Q11: anger management|argument|irony|sarcasm|therapist | R11: http://www.imdb.com/title/tt1986770/?ref_=fn_tt_tt_1 | S11: 54 | T11: English | U11: USA | V11: Unrated | Y11: 701 | Z11: 6.7 | AA11: 1.78 | AB11: 0
A12: Color | C12: 79 | D12: 22 | F12: 424 | G12: Kaitlin Olson | H12: 813 | J12: Comedy | K12: Rob McElhenney | L12: It's Always Sunny in Philadelphia | M12: 133415 | N12: 1784 | O12: Glenn Howerton | P12: 5 | Q12: alcohol|bad taste humour|crude humor|loser|self obsession | R12: http://www.imdb.com/title/tt0472954/?ref_=fn_tt_tt_1 | S12: 151 | T12: English | U12: USA | V12: TV-MA | Y12: 547 | Z12: 8.8 | AA12: 1.33 | AB12: 0
A13: Color | C13: 5 | D13: 23 | F13: 218 | G13: Tiffany Thornton | H13: 254 | J13: Comedy|Family|Romance | K13: Doug Brochu | L13: Sonny with a Chance | M13: 7673 | N13: 915 | O13: Brandon Mychal Smith | P13: 1 | Q13: cafeteria|female protagonist|rival|teenage girl|teenager | R13: http://www.imdb.com/title/tt1252374/?ref_=fn_tt_tt_1 | S13: 47 | T13: English | U13: USA | V13: TV-G | Y13: 248 | Z13: 6.1 | AA13: 1.33 | AB13: 325
A14: Color | C14: 47 | D14: 23 | F14: 265 | G14: James Arnold Taylor | H14: 668 | J14: Action|Adventure|Animation|Drama|Fantasy|Sci-Fi | K14: Dee Bradley Baker | L14: Star Wars: The Clone Wars | M14: 28190 | N14: 1484 | O14: Tom Kane | P14: 0 | Q14: begins with narration|female warrior|inbetwequel|jedi knight|war against machines | R14: http://www.imdb.com/title/tt0458290/?ref_=fn_tt_tt_1 | S14: 73 | T14: English | U14: USA | V14: TV-PG | Y14: 296 | Z14: 7.9 | AA14: 2.35 | AB14: 2000
A15: Color | C15: 3 | D15: 24 | F15: 44 | G15: Johnny Flynn | H15: 381 | J15: Comedy | K15: Antonia Thomas | L15: Lovesick | M15: 2651 | N15: 592 | O15: Hannah Britland | P15: 3 | Q15: blond boy|chlamydia|list|male rear nudity|young couple | R15: http://www.imdb.com/title/tt4051832/?ref_=fn_tt_tt_1 | S15: 18 | T15: English | U15: UK | V15: Unrated | Y15: 102 | Z15: 7.9 | AB15: 0
A16: Color | C16: 6 | D16: 24 | H16: 0 | J16: Action|Adventure|Animation|Family|Fantasy | K16: Pablo Sevilla | L16: Yu-Gi-Oh! Duel Monsters | M16: 12417 | N16: 0 | P16: 0 | Q16: anime|based on manga|hero|surrealism|zen | R16: http://www.imdb.com/title/tt0249327/?ref_=fn_tt_tt_1 | S16: 51 | T16: Japanese | U16: Japan | V16: Unrated | Z16: 7 | AB16: 124
A17: Color | C17: 15 | D17: 25 | F17: 220 | G17: Belinda Stewart-Wilson | H17: 229 | J17: Comedy|Romance | K17: Simon Bird | L17: The Inbetweeners | M17: 55987 | N17: 1239 | O17: James Buckley | P17: 0 | Q17: black comedy|bully|friend|house|practical joke | R17: http://www.imdb.com/title/tt1220617/?ref_=fn_tt_tt_1 | S17: 42 | T17: English | U17: UK | V17: TV-14 | Y17: 223 | Z17: 8.4 | AA17: 1.78 | AB17: 0
A18: Black and White | C18: 31 | D18: 25 | F18: 474 | G18: Agnes Moorehead | H18: 1000 | J18: Comedy|Family|Fantasy | K18: Elizabeth Montgomery | L18: Bewitched | M18: 11427 | N18: 2614 | O18: Dick York | P18: 1 | Q18: connecticut|magic|marriage|witch|witchcraft | R18: http://www.imdb.com/title/tt0057733/?ref_=fn_tt_tt_1 | S18: 71 | T18: English | U18: USA | V18: TV-G | Y18: 960 | Z18: 7.6 | AA18: 1.33 | AB18: 0
A19: Color | B19: Bill Melendez | C19: 43 | D19: 25 | E19: 36 | F19: 27 | G19: Bill Melendez | H19: 39 | J19: Animation|Comedy|Family | K19: Peter Robbins | L19: A Charlie Brown Christmas | M19: 21826 | N19: 139 | O19: Christopher Shea | P19: 0 | Q19: christmas|christmas tree|commercialism|meaning of christmas|tree | R19: http://www.imdb.com/title/tt0059026/?ref_=fn_tt_tt_1 | S19: 126 | T19: English | U19: USA | V19: TV-G | W19: 150000 | X19: 1965 | Y19: 36 | Z19: 8.4 | AA19: 1.33 | AB19: 0
A20: Color | C20: 55 | D20: 25 | F20: 395 | G20: Jamie Farr | H20: 443 | J20: Comedy|Drama|War | K20: David Ogden Stiers | L20: M*A*S*H | M20: 36265 | N20: 2195 | O20: Mike Farrell | P20: 5 | Q20: colonel|doctor|korean war|major|nurse | R20: http://www.imdb.com/title/tt0068098/?ref_=fn_tt_tt_1 | S20: 147 | T20: English | U20: USA | V20: TV-PG | Y20: 421 | Z20: 8.4 | AA20: 1.33 | AB20: 0
A21: Color | C21: 19 | D21: 27 | F21: 201 | G21: Riley Keough | H21: 934 | J21: Drama | K21: Mary Lynn Rajskub | L21: The Girlfriend Experience | M21: 3282 | N21: 1961 | O21: Paul Sparks | P21: 0 | Q21: escort|female nudity|friendship|money|sex scene | R21: http://www.imdb.com/title/tt3846642/?ref_=fn_tt_tt_1 | S21: 17 | T21: English | U21: USA | V21: TV-MA | Y21: 691 | Z21: 7.3 | AB21: 632
A22: Color | C22: 52 | D22: 28 | F22: 576 | G22: Kevin Connolly | H22: 680 | J22: Comedy|Drama | K22: Debi Mazar | L22: Entourage | M22: 135643 | N22: 2867 | O22: Kevin Dillon | P22: 2 | Q22: actor|fame|friendship between men|hollywood california|sitcom | R22: http://www.imdb.com/title/tt0387199/?ref_=fn_tt_tt_1 | S22: 145 | T22: English | U22: USA | V22: TV-MA | Y22: 638 | Z22: 8.5 | AA22: 1.78 | AB22: 0
A23: Color | C23: 1 | D23: 30 | F23: 140 | G23: Katherine Kelly Lang | H23: 177 | J23: Drama|Romance | K23: Ronn Moss | L23: The Bold and the Beautiful | M23: 5478 | N23: 639 | O23: Hunter Tylo | P23: 0 | Q23: beverly hills california|family relationships|los angeles california|soap opera | R23: http://www.imdb.com/title/tt0092325/?ref_=fn_tt_tt_1 | S23: 54 | T23: English | U23: USA | V23: TV-14 | Y23: 170 | Z23: 3.5 | AA23: 1.78 | AB23: 748
A24: Color | C24: 3 | D24: 30 | F24: 12 | G24: Melissa Altro | H24: 51 | J24: Animation|Comedy|Family | K24: Bruce Dinsmore | L24: Arthur | M24: 8495 | N24: 108 | O24: Daniel Brochu | P24: 0 | Q24: based on children's book|best friend|character name in title|friend|one word title | R24: http://www.imdb.com/title/tt0169414/?ref_=fn_tt_tt_1 | S24: 43 | T24: English | U24: Canada | V24: TV-Y | Y24: 21 | Z24: 7.4 | AA24: 1.33 | AB24: 301
A25: Color | C25: 3 | D25: 30 | F25: 295 | G25: David Mann | H25: 607 | J25: Comedy | K25: Lamman Rucker | L25: Meet the Browns | M25: 1922 | N25: 1530 | O25: Denise Boutte | P25: 2 | Q25: african american|character name in title|family relationships|sitcom | R25: http://www.imdb.com/title/tt1319598/?ref_=fn_tt_tt_1 | S25: 20 | T25: English | U25: USA | V25: Unrated | Y25: 378 | Z25: 3.5 | AA25: 1.85 | AB25: 211
A26: Color | C26: 4 | D26: 30 | F26: 359 | G26: Kaitlyn Dever | H26: 995 | J26: Comedy | K26: Hector Elizondo | L26: Last Man Standing | M26: 15114 | N26: 2465 | O26: Nancy Travis | P26: 1 | Q26: family relationships|husband wife relationship|live studio audience|sitcom|three word title | R26: http://www.imdb.com/title/tt1828327/?ref_=fn_tt_tt_1 | S26: 87 | T26: English | U26: USA | V26: TV-PG | Y26: 363 | Z26: 7.4 | AA26: 1.78 | AB26: 0
A27: Black and White | C27: 4 | D27: 30 | F27: 253 | G27: Gavin MacLeod | H27: 870 | J27: Comedy|War | K27: Tim Conway | L27: McHale's Navy | M27: 1558 | N27: 1610 | O27: Bob Hastings | P27: 1 | Q27: american soldier|naval uniform|navy|patrol boat|uniform | R27: http://www.imdb.com/title/tt0055689/?ref_=fn_tt_tt_1 | S27: 18 | T27: English | U27: USA | V27: TV-G | Y27: 284 | Z27: 7.5 | AA27: 1.33 | AB27: 455
A28: Color | C28: 7 | D28: 30 | F28: 265 | G28: Jennifer Hale | H28: 971 | J28: Action|Animation|Comedy|Family|Fantasy|Sci-Fi | K28: Elizabeth Daily | L28: The Powerpuff Girls | M28: 23664 | N28: 2346 | O28: Tom Kane | P28: 0 | Q28: campy|castle thunder|female hero|female protagonist|monster | R28: http://www.imdb.com/title/tt0175058/?ref_=fn_tt_tt_1 | S28: 60 | T28: English | U28: USA | V28: TV-Y7 | Y28: 918 | Z28: 7.2 | AA28: 1.33 | AB28: 581
A29: Black and White | C29: 15 | D29: 30 | F29: 94 | G29: Art Carney | H29: 491 | J29: Comedy|Family | K29: Jackie Gleason | L29: The Honeymooners | M29: 3446 | N29: 812 | O29: Joyce Randolph | P29: 4 | Q29: 1950s|bus driver|money scheme|poverty|sewer | R29: http://www.imdb.com/title/tt0042114/?ref_=fn_tt_tt_1 | S29: 31 | T29: English | U29: USA | V29: Unrated | Y29: 154 | Z29: 8.7 | AA29: 1.33 | AB29: 459
A30: Color | C30: 19 | D30: 30 | F30: 424 | G30: Tim Daly | H30: 685 | J30: Comedy|Drama | K30: Steven Weber | L30: Wings | M30: 7646 | N30: 1884 | O30: Amy Yasbeck | P30: 5 | Q30: 1990s|brother brother relationship|nantucket island|one word title|sister sister relationship | R30: http://www.imdb.com/title/tt0098948/?ref_=fn_tt_tt_1 | S30: 56 | T30: English | U30: USA | V30: Unrated | Y30: 511 | Z30: 7.3 | AA30: 1.33 | AB30: 1000
A31: Color | C31: 46 | D31: 30 | F31: 479 | G31: Kristin Davis | H31: 962 | J31: Comedy|Romance | K31: Chris Noth | L31: Sex and the City | M31: 80025 | N31: 2558 | O31: Cynthia Nixon | P31: 0 | Q31: casual sex|friendship|friendship between women|gay|singles | R31: http://www.imdb.com/title/tt0159206/?ref_=fn_tt_tt_1 | S31: 238 | T31: English | U31: USA | V31: TV-MA | Y31: 722 | Z31: 7 | AA31: 1.33 | AB31: 0
A32: Color | C32: 110 | D32: 30 | F32: 215 | G32: Mark Feuerstein | H32: 909 | J32: Comedy | K32: Leah Remini | L32: Fired Up | M32: 114 | N32: 1557 | O32: Sharon Lawrence | P32: 2 | Q32: sitcom | R32: http://www.imdb.com/title/tt0118315/?ref_=fn_tt_tt_1 | S32: 6 | T32: English | U32: USA | V32: Unrated | Y32: 417 | Z32: 6.7 | AA32: 1.33 | AB32: 4
A33: Color | C33: 110 | D33: 30 | F33: 9 | G33: George Coulouris | H33: 310 | J33: Drama|Family | K33: Peter Vaughan | L33: The Doombolt Chase | M33: 18 | N33: 344 | O33: Ewen Solon | P33: 4 | R33: http://www.imdb.com/title/tt0166038/?ref_=fn_tt_tt_1 | S33: 156 | T33: English | U33: UK | V33: Unrated | Y33: 11 | Z33: 7.2 | AB33: 0
A34: Color | C34: 110 | D34: 30 | F34: 223 | G34: David DeLuise | H34: 775 | J34: Comedy | K34: Eric Lloyd | L34: Jesse | M34: 954 | N34: 1713 | O34: Bruno Campos | P34: 8 | Q34: 1990s|brother sister relationship|female protagonist|single mother|sitcom | R34: http://www.imdb.com/title/tt0156196/?ref_=fn_tt_tt_1 | S34: 14 | T34: English | U34: USA | V34: Unrated | Y34: 275 | Z34: 5.9 | AB34: 57
A35: Color | B35: Randall Miller | C35: 1 | D35: 34 | E35: 19 | F35: 362 | G35: Elden Henson | H35: 882 | I35: 333658 | J35: Comedy|Family|Musical|Romance|Short | K35: William Hurt | L35: Marilyn Hotchkiss' Ballroom Dancing and Charm School | M35: 97 | N35: 1967 | O35: Michael Bower | P35: 0 | Q35: student film|wonder years | R35: http://www.imdb.com/title/tt0283465/?ref_=fn_tt_tt_1 | S35: 2 | T35: English | U35: USA | V35: Unrated | W35: 34000 | X35: 1990 | Y35: 577 | Z35: 7.1 | AB35: 16
A36: Color | B36: Jason Naumann | C36: 110 | D36: 35 | E36: 2 | F36: 152 | G36: Kate Flannery | H36: 338 | J36: Comedy|Short | K36: Victoria Jackson | L36: Jesus People | M36: 31 | N36: 968 | O36: Tim Bagley | P36: 5 | Q36: mockumentary|single camera|subtle comedy | R36: http://www.imdb.com/title/tt1003002/?ref_=fn_tt_tt_1 | S36: 156 | T36: English | U36: USA | V36: Unrated | X36: 2007 | Y36: 219 | Z36: 6.9 | AB36: 0
A37: Color | B37: Sam Raimi | C37: 252 | D37: 37 | E37: 0 | F37: 199 | G37: Dan Hicks | H37: 634 | I37: 5923044 | J37: Comedy|Fantasy|Horror|Thriller | K37: Ted Raimi | L37: Evil Dead II | M37: 113451 | N37: 1347 | O37: Kassie Wesley DePaiva | P37: 0 | Q37: cabin|cabin in the woods|demon|evil dead|woods | R37: http://www.imdb.com/title/tt0092991/?ref_=fn_tt_tt_1 | S37: 537 | T37: English | U37: USA | V37: X | W37: 3600000 | X37: 1987 | Y37: 328 | Z37: 7.8 | AA37: 1.85 | AB37: 0
A38: Color | C38: 68 | D38: 40 | F38: 476 | G38: T.J. Thyne | H38: 1000 | J38: Comedy|Crime|Drama|Mystery|Romance | K38: Michaela Conlin | L38: Bones | M38: 111506 | N38: 2198 | O38: Tamara Taylor | P38: 2 | Q38: anthropologist|fbi|fbi agent|forensics|investigation | R38: http://www.imdb.com/title/tt0460627/?ref_=fn_tt_tt_1 | S38: 173 | T38: English | U38: USA | V38: TV-14 | Y38: 722 | Z38: 7.9 | AA38: 1.78 | AB38: 0
A39: Color | C39: 1 | D39: 41 | F39: 2 | G39: Marian Dziedziel | H39: 70 | J39: Action|Crime|Drama|Thriller | K39: Jacek Koman | L39: The Border | M39: 271 | N39: 74 | O39: Jaroslaw Boberek | P39: 4 | R39: http://www.imdb.com/title/tt4048942/?ref_=fn_tt_tt_1 | S39: 2 | T39: Polish | U39: Poland | V39: Unrated | Y39: 2 | Z39: 7.4 | AB39: 64
A40: Color | B40: Ronan Chapalain | C40: 7 | D40: 41 | E40: 0 | F40: 0 | G40: Guillaume Denaiffe | H40: 55 | I40: 4074023 | J40: Documentary | K40: Norbert Ferrer | L40: Sea Rex 3D: Journey to a Prehistoric World | M40: 296 | N40: 55 | O40: Chloe Hollings | P40: 0 | Q40: 3d|imax|plesiosaur|sea|water | R40: http://www.imdb.com/title/tt1529567/?ref_=fn_tt_tt_1 | S40: 4 | T40: English | U40: UK | V40: Unrated | W40: 5000000 | X40: 2010 | Y40: 0 | Z40: 6.9 | AA40: 1.78 | AB40: 89
A41: Color | C41: 7 | D41: 42 | F41: 535 | G41: Mary Elizabeth Mastrantonio | H41: 766 | J41: Crime|Drama|Sci-Fi|Thriller | K41: Colin Salmon | L41: Limitless | M41: 38177 | N41: 2707 | O41: Jake McDorman | P41: 2 | Q41: brain capacity|fbi|fictional drug|intelligence|taking a pill | R41: http://www.imdb.com/title/tt4422836/?ref_=fn_tt_tt_1 | S41: 131 | T41: English | U41: USA | V41: TV-14 | Y41: 638 | Z41: 7.9 | AA41: 1.78 | AB41: 11000
A42: Color | B42: Jean-Jacques Mantello | C42: 9 | D42: 42 | E42: 0 | G42: Daryl Hannah | H42: 844 | I42: 7518876 | J42: Adventure|Documentary|Short | K42: Charlotte Rampling | L42: Dolphins and Whales 3D: Tribes of the Ocean | M42: 172 | N42: 844 | P42: 0 | Q42: 3d in title|animal in title|digit in title|dolphin|manatee | R42: http://www.imdb.com/title/tt0996382/?ref_=fn_tt_tt_1 | S42: 5 | T42: English | U42: UK | V42: Unrated | W42: 6000000 | X42: 2008 | Y42: 0 | Z42: 6.5 | AA42: 1.78 | AB42: 28
A43: Color | C43: 13 | D43: 42 | F43: 442 | G43: Kirk Acevedo | H43: 757 | J43: Adventure|Drama|Mystery|Sci-Fi|Thriller | K43: Amanda Schull | L43: 12 Monkeys | M43: 20839 | N43: 3309 | O43: Tom Noonan | P43: 0 | Q43: epidemic|mission|paradox|plague|virus | R43: http://www.imdb.com/title/tt3148266/?ref_=fn_tt_tt_1 | S43: 56 | T43: English | U43: USA | V43: TV-14 | Y43: 641 | Z43: 7.6 | AA43: 1.78 | AB43: 12000
A44: Color | C44: 22 | D44: 42 | F44: 496 | G44: Gabourey Sidibe | H44: 912 | J44: Drama|Music | K44: Ta'Rhonda Jones | L44: Empire | M44: 27418 | N44: 4337 | O44: Malik Yoba | P44: 2 | Q44: music business|new york city|record executive|record label|singer | R44: http://www.imdb.com/title/tt3228904/?ref_=fn_tt_tt_1 | S44: 92 | T44: English | U44: USA | V44: TV-14 | Y44: 906 | Z44: 7.8 | AA44: 1.78 | AB44: 14000
A45: Color | C45: 26 | D45: 42 | F45: 376 | G45: Eric McCormack | H45: 1000 | J45: Crime|Drama|Mystery|Thriller | K45: LeVar Burton | L45: Perception | M45: 15612 | N45: 2240 | O45: Scott Wolf | P45: 1 | R45: http://www.imdb.com/title/tt1714204/?ref_=fn_tt_tt_1 | S45: 29 | T45: English | U45: USA | V45: TV-14 | Y45: 440 | Z45: 7.5 | AA45: 1.78 | AB45: 0
A46: Color | C46: 5 | D46: 43 | F46: 452 | G46: Aimee Garcia | H46: 778 | J46: Action|Comedy|Crime | K46: Jon Foo | L46: Rush Hour | M46: 2185 | N46: 2255 | O46: Wendie Malick | P46: 2 | R46: http://www.imdb.com/title/tt4085584/?ref_=fn_tt_tt_1 | S46: 30 | T46: English | U46: USA | V46: TV-14 | Y46: 618 | Z46: 5.8 | AA46: 1.78 | AB46: 0
A47: Color | C47: 5 | D47: 43 | F47: 298 | G47: Indiana Evans | H47: 562 | J47: Crime|Drama | K47: Dan Fogler | L47: Secrets and Lies | M47: 6762 | N47: 1587 | O47: KaDee Strickland | P47: 0 | R47: http://www.imdb.com/title/tt3516878/?ref_=fn_tt_tt_1 | S47: 27 | T47: English | U47: USA | V47: Unrated | Y47: 560 | Z47: 7.7 | AA47: 1.78 | AB47: 2000
A48: Color | C48: 12 | D48: 43 | F48: 218 | G48: Matt Ryan | H48: 1000 | J48: Drama|Fantasy|Horror|Thriller | K48: Harold Perrineau | L48: Constantine | M48: 36919 | N48: 1990 | O48: Charles Halford | P48: 1 | Q48: based on comic|based on comic book|dc arrowverse|dc comics|supernatural | R48: http://www.imdb.com/title/tt3489184/?ref_=fn_tt_tt_1 | S48: 94 | T48: English | U48: USA | V48: TV-14 | Y48: 560 | Z48: 7.5 | AA48: 1.78 | AB48: 10000
A49: Color | C49: 23 | D49: 43 | F49: 576 | G49: Tracy Spiridakos | H49: 2000 | J49: Action|Adventure|Drama|Sci-Fi | K49: Billy Burke | L49: Revolution | M49: 72017 | N49: 5052 | O49: David Lyons | P49: 6 | Q49: 2020s|near future|one word series title|post apocalypse|year 2027 | R49: http://www.imdb.com/title/tt2070791/?ref_=fn_tt_tt_1 | S49: 323 | T49: English | U49: USA | V49: TV-14 | Y49: 821 | Z49: 6.7 | AA49: 1.78 | AB49: 17000
A50: Color | C50: 28 | D50: 43 | F50: 600 | G50: Tony Curran | H50: 3000 | J50: Action|Drama|Sci-Fi | K50: Julie Benz | L50: Defiance | M50: 33535 | N50: 5381 | O50: Grant Bowler | P50: 3 | Q50: alien|alien invasion|planet invasion|post apocalypse|year 2046 | R50: http://www.imdb.com/title/tt2189221/?ref_=fn_tt_tt_1 | S50: 149 | T50: English | U50: USA | V50: TV-MA | Y50: 845 | Z50: 7 | AA50: 1.78 | AB50: 0
A51: Color | C51: 43 | D51: 43 | F51: 319 | G51: Valorie Curry | H51: 841 | J51: Crime|Drama|Mystery|Thriller | K51: Natalie Zea | L51: The Following | M51: 73839 | N51: 1753 | O51: Sam Underwood | P51: 1 | Q51: cult|fbi|hideout|prison escape|serial killer | R51: http://www.imdb.com/title/tt2071645/?ref_=fn_tt_tt_1 | S51: 359 | T51: English | U51: USA | V51: TV-14 | Y51: 593 | Z51: 7.5 | AA51: 1.78 | AB51: 32000
A52: Color | C52: 110 | D52: 43 | F52: 211 | G52: Jenni 'Jwoww' Farley | H52: 341 | J52: Comedy|Drama|Reality-TV|Romance | K52: Nicole 'Snooki' Polizzi | L52: Gone, Baby, Gone | M52: 29 | N52: 1462 | O52: Paul 'Pauly D' DelVecchio | P52: 1 | Q52: lifestyle | R52: http://www.imdb.com/title/tt1697237/?ref_=fn_tt_tt_1 | S52: 156 | T52: English | U52: Unknown | V52: TV-14 | Y52: 230 | Z52: 6.6 | AA52: 1.33 | AB52: 0
A53: Color | C53: 7 | D53: 44 | F53: 246 | G53: Megan Hilty | H53: 786 | J53: Comedy|Drama|Horror|Sci-Fi|Thriller | K53: Danny Pino | L53: BrainDead | M53: 2948 | N53: 1551 | O53: Zach Grenier | P53: 0 | Q53: brains|exploding head|politician|swarm behavior|washington d.c. | R53: http://www.imdb.com/title/tt4877736/?ref_=fn_tt_tt_1 | S53: 28 | T53: English | U53: USA | V53: Unrated | Y53: 341 | Z53: 7.9 | AA53: 1.78 | AB53: 3000
A54: Color | C54: 20 | D54: 44 | F54: 650 | G54: Melinda Clarke | H54: 828 | J54: Comedy|Drama|Romance | K54: Peter Gallagher | L54: The O.C. | M54: 65785 | N54: 2546 | O54: Tate Donovan | P54: 8 | Q54: california|lawyer|love|orange county california|wealth | R54: http://www.imdb.com/title/tt0362359/?ref_=fn_tt_tt_1 | S54: 281 | T54: English | U54: USA | V54: TV-PG | Y54: 787 | Z54: 7.5 | AA54: 1.78 | AB54: 0
A55: Color | C55: 38 | D55: 44 | F55: 816 | G55: Dulé Hill | H55: 1000 | J55: Comedy|Crime|Mystery | K55: Corbin Bernsen | L55: Psych | M55: 67315 | N55: 4092 | O55: Timothy Omundson | P55: 2 | Q55: best friend|friend|police|police department|psychic | R55: http://www.imdb.com/title/tt0491738/?ref_=fn_tt_tt_1 | S55: 127 | T55: English | U55: USA | V55: TV-PG | Y55: 922 | Z55: 8.4 | AA55: 1.78 | AB55: 0
A56: Color | C56: 47 | D56: 44 | F56: 724 | G56: Jason Dohring | H56: 937 | J56: Crime|Drama|Mystery | K56: Francis Capra | L56: Veronica Mars | M56: 55524 | N56: 3318 | O56: Enrico Colantoni | P56: 1 | Q56: best friend|high school|private detective|sheriff|student | R56: http://www.imdb.com/title/tt0412253/?ref_=fn_tt_tt_1 | S56: 315 | T56: English | U56: USA | V56: TV-14 | Y56: 828 | Z56: 8.4 | AA56: 1.78 | AB56: 0
A57: Color | C57: 51 | D57: 44 | F57: 690 | G57: Aimee Teegarden | H57: 971 | J57: Drama|Sport | K57: Zach Gilford | L57: Friday Night Lights | M57: 42746 | N57: 3418 | O57: Scott Porter | P57: 1 | Q57: football|football coach|high school|small town|texas | R57: http://www.imdb.com/title/tt0758745/?ref_=fn_tt_tt_1 | S57: 257 | T57: English | U57: USA | V57: TV-14 | Y57: 741 | Z57: 8.7 | AA57: 1.78 | AB57: 0
A58: Color | C58: 77 | D58: 44 | F58: 72 | G58: Don S. Davis | H58: 847 | J58: Action|Adventure|Drama|Sci-Fi | K58: Christopher Judge | L58: Stargate SG-1 | M58: 63982 | N58: 1359 | O58: Gary Jones | P58: 4 | Q58: 2000s|21st century|alternate history|message from outer space|military | R58: http://www.imdb.com/title/tt0118480/?ref_=fn_tt_tt_1 | S58: 181 | T58: English | U58: USA | V58: TV-14 | W58: 1400000 | Y58: 440 | Z58: 8.4 | AA58: 1.33 | AB58: 0
A59: Color | C59: 96 | D59: 44 | F59: 970 | G59: Alyson Hannigan | H59: 4000 | J59: Action|Drama|Fantasy|Romance | K59: Sarah Michelle Gellar | L59: Buffy the Vampire Slayer | M59: 101902 | N59: 7970 | O59: Emma Caulfield | P59: 0 | Q59: action heroine|coming of age|destiny|double life|vampire | R59: http://www.imdb.com/title/tt0118276/?ref_=fn_tt_tt_1 | S59: 665 | T59: English | U59: USA | V59: TV-14 | W59: 2300000 | Y59: 3000 | Z59: 8.2 | AA59: 1.33 | AB59: 6000
A60: Color | C60: 103 | D60: 44 | F60: 148 | G60: Scott Thompson | H60: 544 | J60: Crime|Drama|Horror|Mystery|Thriller | K60: Caroline Dhavernas | L60: Hannibal | M60: 159910 | N60: 996 | O60: Hettienne Park | P60: 1 | Q60: blood|cannibalism|fbi|manipulation|psychiatrist | R60: http://www.imdb.com/title/tt2243973/?ref_=fn_tt_tt_1 | S60: 270 | T60: English | U60: USA | V60: TV-14 | Y60: 183 | Z60: 8.6 | AA60: 1.78 | AB60: 59000
A61: Color | C61: 1 | D61: 45 | F61: 119 | G61: Ash Cook | H61: 773 | J61: Drama|Thriller | K61: James Nesbitt | L61: The Secret | M61: 653 | N61: 1393 | O61: Genevieve O'Reilly | P61: 3 | Q61: adultery|baptist church|dentist|double murder|tv mini series | R61: http://www.imdb.com/title/tt5116280/?ref_=fn_tt_tt_1 | S61: 4 | T61: English | U61: UK | V61: Unrated | Y61: 133 | Z61: 7.3 | AB61: 405
A62: Color | C62: 2 | D62: 45 | F62: 132 | G62: Gemma Jones | H62: 416 | J62: Crime|Drama | K62: Bernard Hill | L62: Unforgotten | M62: 1824 | N62: 1816 | O62: Nicola Walker | P62: 2 | R62: http://www.imdb.com/title/tt4192812/?ref_=fn_tt_tt_1 | S62: 9 | T62: English | U62: UK | V62: Unrated | Y62: 171 | Z62: 7.9 | AB62: 0
A63: Color | B63: Richard Rich | C63: 2 | D63: 45 | E63: 24 | F63: 29 | G63: Kate Higgins | H63: 122 | J63: Action|Adventure|Animation|Comedy|Drama|Family|Fantasy|Thriller | K63: Debi Derryberry | L63: Alpha and Omega 4: The Legend of the Saw Toothed Cave | M63: 192 | N63: 236 | O63: Cindy Robinson | P63: 0 | Q63: blindness|cave|spirit|wolf|wolf cub | R63: http://www.imdb.com/title/tt4061848/?ref_=fn_tt_tt_1 | S63: 6 | T63: Unknown | U63: USA | V63: Unrated | W63: 7000000 | X63: 2014 | Y63: 35 | Z63: 6 | AB63: 41
A64: Color | C64: 12 | D64: 45 | F64: 0 | G64: Brent Sexton | H64: 374 | J64: Crime|Drama|Mystery | K64: Adam Arkin | L64: Life | M64: 29450 | N64: 504 | O64: Damian Lewis | P64: 1 | Q64: cop|murder|partner|police|protective male | R64: http://www.imdb.com/title/tt0874936/?ref_=fn_tt_tt_1 | S64: 67 | T64: English | U64: USA | V64: Unrated | Y64: 130 | Z64: 8.3 | AB64: 0
A65: Color | C65: 20 | D65: 45 | F65: 15 | G65: Trond Fausa | H65: 422 | J65: Comedy|Crime|Drama | K65: Steven Van Zandt | L65: Lilyhammer | M65: 19164 | N65: 537 | O65: Tommy Karlsen | P65: 0 | Q65: mafia|mob|norway|steve|van | R65: http://www.imdb.com/title/tt1958961/?ref_=fn_tt_tt_1 | S65: 79 | T65: English | U65: Norway | V65: TV-MA | W65: 34000000 | Y65: 57 | Z65: 8.1 | AA65: 1.78 | AB65: 16000
A66: Color | C66: 20 | D66: 45 | F66: 260 | G66: Bobby Campo | H66: 460 | J66: Crime|Drama|Horror|Mystery|Thriller | K66: Bex Taylor-Klaus | L66: Scream: The TV Series | M66: 18058 | N66: 2380 | O66: Jason Wiles | P66: 0 | Q66: generation y|millennial generation|murder|teenage girl|throat slitting | R66: http://www.imdb.com/title/tt3921180/?ref_=fn_tt_tt_1 | S66: 68 | T66: English | U66: USA | V66: TV-14 | Y66: 292 | Z66: 7.3 | AA66: 1.78 | AB66: 0
A67: Color | C67: 39 | D67: 45 | F67: 160 | G67: Katia Winter | H67: 898 | J67: Adventure|Drama|Fantasy|Mystery|Thriller | K67: Nicole Beharie | L67: Sleepy Hollow | M67: 49049 | N67: 1430 | O67: Lyndie Greenwood | P67: 0 | Q67: apocalypse|death|husband wife relationship|mother son relationship|murder | R67: http://www.imdb.com/title/tt2647544/?ref_=fn_tt_tt_1 | S67: 110 | T67: English | U67: USA | V67: TV-14 | Y67: 372 | Z67: 7.5 | AA67: 1.78 | AB67: 14000
A68: Color | B68: Ole Christian Madsen | C68: 80 | D68: 45 | E68: 28 | F68: 104 | G68: Thure Lindhardt | H68: 573 | I68: 145109 | J68: Drama|History|Thriller|War | K68: Lars Mikkelsen | L68: Flame and Citron | M68: 14247 | N68: 1098 | O68: Christian Berkel | P68: 1 | Q68: danish|double agent|nazi|nazi occupation|resistance | R68: http://www.imdb.com/title/tt0920458/?ref_=fn_tt_tt_1 | S68: 44 | T68: Danish | U68: Denmark | V68: Not Rated | W68: 45000000 | X68: 2008 | Y68: 197 | Z68: 7.3 | AA68: 2.35 | AB68: 0
A69: Color | B69: Don Kempf | C69: 14 | D69: 46 | E69: 0 | F69: 69 | G69: Michael Jordan | H69: 13000 | I69: 18642318 | J69: Documentary|Sport | K69: Bill Murray | L69: Michael Jordan to the Max | M69: 1723 | N69: 13448 | O69: Bob Costas | P69: 0 | Q69: basketball|basketball player|character name in title|chicago bulls|imax | R69: http://www.imdb.com/title/tt0245280/?ref_=fn_tt_tt_1 | S69: 13 | T69: English | U69: USA | V69: Unrated | X69: 2000 | Y69: 366 | Z69: 7.5 | AA69: 1.44 | AB69: 407
A70: Black and White | B70: Andrew Leman | C70: 60 | D70: 47 | E70: 2 | F70: 5 | G70: David Mersault | H70: 19 | J70: Fantasy|Horror|Mystery|Thriller | K70: Dan Novy | L70: The Call of Cthulhu | M70: 6261 | N70: 43 | O70: Barry Lynch | P70: 0 | Q70: 1920s|cthulhu|dream|sailor|silent film | R70: http://www.imdb.com/title/tt0478988/?ref_=fn_tt_tt_1 | S70: 99 | T70: English | U70: USA | V70: Unrated | W70: 50000 | X70: 2005 | Y70: 9 | Z70: 7.3 | AA70: 1.33 | AB70: 0
A71: Color | C71: 6 | D71: 50 | F71: 543 | G71: Sarah Carter | H71: 787 | J71: Action|Crime|Drama|Thriller | K71: Cole Hauser | L71: Rogue | M71: 1781 | N71: 3276 | O71: Derek Luke | P71: 0 | Q71: cheating wife|extramarital affair|female lead|undercover|unfaithfulness | R71: http://www.imdb.com/title/tt2397255/?ref_=fn_tt_tt_1 | S71: 23 | T71: English | U71: USA | V71: Unrated | Y71: 748 | Z71: 6.8 | AB71: 532
A72: Color | C72: 23 | D72: 52 | F72: 114 | G72: Clotilde Hesme | H72: 164 | J72: Drama|Fantasy|Horror|Mystery | K72: Pierre Perrier | L72: The Returned | M72: 15762 | N72: 654 | O72: Céline Sallette | P72: 9 | Q72: france|living dead|serial killer|small town|supernatural | R72: http://www.imdb.com/title/tt2521668/?ref_=fn_tt_tt_1 | S72: 47 | T72: French | U72: France | V72: TV-MA | Y72: 116 | Z72: 8.3 | AA72: 1.78 | AB72: 17000
A73: Color | B73: Joe Kenemore | C73: 110 | D73: 52 | E73: 0 | F73: 0 | G73: Jack Canfield | H73: 8 | J73: Documentary | K73: Bob Proctor | L73: Rise of the Entrepreneur: The Search for a Better Way | M73: 78 | N73: 10 | O73: Eric Worre | P73: 0 | Q73: business|entrepreneur|network marketing | R73: http://www.imdb.com/title/tt4273494/?ref_=fn_tt_tt_1 | S73: 10 | T73: English | U73: USA | V73: G | W73: 450000 | X73: 2014 | Y73: 2 | Z73: 8.2 | AB73: 460
A74: Color | C74: 54 | D74: 53 | F74: 1000 | G74: Adam Goldberg | H74: 4000 | J74: Crime|Drama|Thriller | K74: Kirsten Dunst | L74: Fargo | M74: 170055 | N74: 19949 | O74: Oliver Platt | P74: 0 | Q74: anthology|death|insurance salesman|minnesota|police officer | R74: http://www.imdb.com/title/tt2802850/?ref_=fn_tt_tt_1 | S74: 173 | T74: English | U74: USA | V74: TV-MA | Y74: 1000 | Z74: 9 | AA74: 1.78 | AB74: 61000
A75: Color | B75: Alex Gibney | C75: 84 | D75: 53 | E75: 141 | F75: 23 | G75: George W. Bush | H75: 141 | I75: 274661 | J75: Crime|Documentary|War | K75: Alex Gibney | L75: Taxi to the Dark Side | M75: 10564 | N75: 313 | O75: Greg D'Agostino | P75: 0 | Q75: afghanistan|detainee|guantanamo bay|taxi|torture | R75: http://www.imdb.com/title/tt0854678/?ref_=fn_tt_tt_1 | S75: 40 | T75: English | U75: USA | V75: R | W75: 1000000 | X75: 2007 | Y75: 125 | Z75: 7.7 | AA75: 1.85 | AB75: 0
A76: Color | C76: 10 | D76: 55 | F76: 5 | G76: Fortunato Cerlino | H76: 18 | J76: Crime|Drama|Thriller | K76: Maria Pia Calzone | L76: Gomorrah | M76: 9638 | N76: 39 | O76: Marco D'Amore | P76: 5 | R76: http://www.imdb.com/title/tt2049116/?ref_=fn_tt_tt_1 | S76: 25 | T76: Italian | U76: Italy | V76: TV-MA | Y76: 9 | Z76: 8.7 | AA76: 1.85 | AB76: 0
A77: Color | C77: 53 | D77: 55 | F77: 2 | G77: Olaf Lubaszenko | H77: 20 | I77: 447093 | J77: Drama | K77: Krystyna Janda | L77: Dekalog | M77: 12590 | N77: 25 | O77: Olgierd Lukaszewicz | P77: 0 | Q77: meaning of life|moral challenge|morality|search for meaning|ten commandments | R77: http://www.imdb.com/title/tt0092337/?ref_=fn_tt_tt_1 | S77: 37 | T77: Polish | U77: Poland | V77: TV-MA | Y77: 3 | Z77: 9.1 | AA77: 1.33 | AB77: 0
A78: Color | C78: 53 | D78: 55 | F78: 2 | G78: Olaf Lubaszenko | H78: 20 | I78: 447093 | J78: Drama | K78: Krystyna Janda | L78: Dekalog | M78: 12591 | N78: 25 | O78: Olgierd Lukaszewicz | P78: 0 | Q78: meaning of life|moral challenge|morality|search for meaning|ten commandments | R78: http://www.imdb.com/title/tt0092337/?ref_=fn_tt_tt_1 | S78: 37 | T78: Polish | U78: Poland | V78: TV-MA | Y78: 3 | Z78: 9.1 | AA78: 1.33 | AB78: 0
A79: Color | C79: 68 | D79: 55 | F79: 898 | G79: Kelvin Taylor | H79: 1000 | J79: Action|Adventure|Biography|Drama|History | K79: Peter Mensah | L79: Spartacus: War of the Damned | M79: 173172 | N79: 6091 | O79: Viva Bianca | P79: 2 | Q79: female frontal nudity|female full frontal nudity|gladiator|group sex|slave girl | R79: http://www.imdb.com/title/tt1442449/?ref_=fn_tt_tt_1 | S79: 302 | T79: English | U79: USA | V79: TV-MA | Y79: 939 | Z79: 8.6 | AA79: 1.78 | AB79: 31000
A80: Color | C80: 11 | D80: 58 | F80: 250 | G80: James Norton | H80: 887 | J80: Crime|Drama | K80: Shirley Henderson | L80: Happy Valley | M80: 12848 | N80: 2572 | O80: Sarah Lancashire | P80: 1 | Q80: caravan|police|police sergeant|tied to a chair|yorkshire | R80: http://www.imdb.com/title/tt3428912/?ref_=fn_tt_tt_1 | S80: 59 | T80: English | U80: UK | V80: TV-MA | Y80: 340 | Z80: 8.5 | AA80: 1.78 | AB80: 10000
A81: Color | B81: Chris Marker | C81: 16 | D81: 59 | E81: 121 | F81: 0 | G81: Bertrand Cantat | H81: 27 | J81: Documentary | K81: Marina Vlady | L81: The Case of the Grinning Cat | M81: 352 | N81: 27 | O81: Léon Schwartzenberg | P81: 0 | R81: http://www.imdb.com/title/tt0437123/?ref_=fn_tt_tt_1 | S81: 4 | T81: French | U81: France | V81: Unrated | W81: 150000 | X81: 2004 | Y81: 0 | Z81: 7.4 | AA81: 1.37 | AB81: 44
A82: Color | C82: 1 | D82: 60 | F82: 213 | G82: Alan Autry | H82: 480 | J82: Crime|Drama|Mystery | K82: Carroll O'Connor | L82: In the Heat of the Night | M82: 2258 | N82: 1736 | O82: Crystal R. Fox | P82: 1 | Q82: detective|mississippi|police|police detective|small town | R82: http://www.imdb.com/title/tt0094484/?ref_=fn_tt_tt_1 | S82: 24 | T82: English | U82: USA | V82: Unrated | Y82: 360 | Z82: 7.4 | AA82: 1.33 | AB82: 763
A83: Color | C83: 1 | D83: 60 | F83: 143 | G83: Jon Tenney | H83: 11000 | J83: Comedy|Drama|Romance | K83: Anne Hathaway | L83: Get Real | M83: 415 | N83: 11618 | O83: Debrah Farentino | P83: 5 | Q83: breaking the fourth wall|brother brother relationship|high school friends|imperative in title|skateboard | R83: http://www.imdb.com/title/tt0212662/?ref_=fn_tt_tt_1 | S83: 26 | T83: English | U83: USA | V83: Unrated | Y83: 289 | Z83: 7.3 | AA83: 1.33 | AB83: 43
A84: Color | C84: 3 | D84: 60 | F84: 628 | G84: Kimberly Elise | H84: 897 | J84: Drama|Romance | K84: Jodi Lyn O'Keefe | L84: Hit the Floor | M84: 1641 | N84: 3438 | O84: Logan Browning | P84: 4 | Q84: affair|hip hop|sex scene | R84: http://www.imdb.com/title/tt2368645/?ref_=fn_tt_tt_1 | S84: 11 | T84: English | U84: USA | V84: Unrated | Y84: 637 | Z84: 7 | AB84: 265
A85: Color | C85: 3 | D85: 60 | F85: 762 | G85: Jessika Van | H85: 1000 | J85: Drama|Fantasy|Mystery|Thriller | K85: Joel Courtney | L85: The Messengers | M85: 7210 | N85: 4561 | O85: Riley Smith | P85: 0 | R85: http://www.imdb.com/title/tt3513704/?ref_=fn_tt_tt_1 | S85: 57 | T85: English | U85: USA | V85: Unrated | Y85: 921 | Z85: 6.6 | AA85: 1.78 | AB85: 0
A86: Color | C86: 4 | D86: 60 | F86: 398 | G86: Brittany Curran | H86: 629 | J86: Drama|Mystery|Thriller | K86: Grey Damon | L86: Twisted | M86: 7945 | N86: 2758 | O86: Aaron Hill | P86: 2 | R86: http://www.imdb.com/title/tt2355844/?ref_=fn_tt_tt_1 | S86: 22 | T86: English | U86: USA | V86: Unrated | Y86: 512 | Z86: 7.5 | AA86: 1.78 | AB86: 915
A87: Color | C87: 4 | D87: 60 | F87: 23 | G87: Amanda Mealing | H87: 40 | J87: Drama | K87: Susan Hampshire | L87: The Grand | M87: 437 | N87: 158 | O87: Tim Healy | P87: 0 | Q87: concierge|front desk|hotel|maid|prostitute | R87: http://www.imdb.com/title/tt0118327/?ref_=fn_tt_tt_1 | S87: 20 | T87: English | U87: UK | V87: Unrated | Y87: 37 | Z87: 7.6 | AA87: 1.33 | AB87: 450
A88: Color | C88: 5 | D88: 60 | H88: 98 | J88: Game-Show|Reality-TV|Romance | K88: Chris Harrison | L88: The Bachelor | M88: 4398 | N88: 98 | P88: 0 | Q88: bachelor|seeking love|single guy|tv host|women rivals for man | R88: http://www.imdb.com/title/tt0313038/?ref_=fn_tt_tt_1 | S88: 33 | T88: English | U88: USA | V88: Unrated | W88: 3000000 | Z88: 2.9 | AB88: 141
A89: Black and White | B89: Jim Chuchu | C89: 6 | D89: 60 | E89: 0 | F89: 4 | G89: Olwenya Maina | H89: 147 | J89: Drama | K89: Paul Ogola | L89: Stories of Our Lives | M89: 70 | N89: 170 | O89: Mugambi Nthiga | P89: 0 | R89: http://www.imdb.com/title/tt3973612/?ref_=fn_tt_tt_1 | S89: 1 | T89: Swahili | U89: Kenya | V89: Unrated | W89: 15000 | X89: 2014 | Y89: 19 | Z89: 7.4 | AB89: 45
A90: Color | C90: 8 | D90: 60 | F90: 551 | G90: Daniella Alonso | H90: 1000 | J90: Crime|Drama | K90: Dorian Missick | L90: Animal Kingdom | M90: 3673 | N90: 3026 | O90: Ellen Barkin | P90: 0 | Q90: based on film|brother brother relationship|crime family|remake|southern california | R90: http://www.imdb.com/title/tt5574490/?ref_=fn_tt_tt_1 | S90: 23 | T90: English | U90: USA | V90: Unrated | Y90: 557 | Z90: 8.1 | AA90: 1.78 | AB90: 0
A91: Color | C91: 8 | D91: 60 | F91: 109 | G91: Tucker Smallwood | H91: 210 | J91: Drama|Sci-Fi | K91: James Morrison | L91: Space: Above and Beyond | M91: 6381 | N91: 611 | O91: Kristen Cloke | P91: 0 | Q91: alien|born in vitro|in vitro fertilization|marine|outer space | R91: http://www.imdb.com/title/tt0112173/?ref_=fn_tt_tt_1 | S91: 79 | T91: English | U91: USA | V91: Unrated | W91: 5000000 | Y91: 121 | Z91: 7.7 | AA91: 1.33 | AB91: 963
A92: Color | C92: 9 | D92: 60 | F92: 468 | G92: Joan Allen | H92: 971 | J92: Drama|Mystery | K92: Zach Gilford | L92: The Family | M92: 3322 | N92: 3295 | O92: Liam James | P92: 4 | Q92: family drama|lie|missing child|political campaign|secret | R92: http://www.imdb.com/title/tt4428038/?ref_=fn_tt_tt_1 | S92: 30 | T92: English | U92: USA | V92: TV-PG | Y92: 805 | Z92: 7.5 | AA92: 1.78 | AB92: 0
A93: Color | C93: 9 | D93: 60 | F93: 460 | G93: Philip Winchester | H93: 666 | J93: Action|Crime|Drama|Thriller | K93: Nick Wechsler | L93: The Player | M93: 5817 | N93: 4043 | O93: Jeff Marlow | P93: 2 | Q93: bet|friend|pit boss|secret|surveillance | R93: http://www.imdb.com/title/tt4474310/?ref_=fn_tt_tt_1 | S93: 25 | T93: English | U93: USA | V93: TV-14 | Y93: 579 | Z93: 7.1 | AA93: 1.78 | AB93: 0
A94: Color | C94: 9 | D94: 60 | F94: 904 | G94: Dylan Minnette | H94: 1000 | J94: Drama|Fantasy | K94: Holly Hunter | L94: Saving Grace | M94: 3852 | N94: 5203 | O94: Bokeem Woodbine | P94: 1 | Q94: catholic|death row|inmate|oklahoma city|sexual promiscuity | R94: http://www.imdb.com/title/tt0830900/?ref_=fn_tt_tt_1 | S94: 47 | T94: English | U94: USA | V94: TV-MA | Y94: 1000 | Z94: 7.5 | AA94: 1.78 | AB94: 634
A95: Color | C95: 11 | D95: 60 | F95: 652 | G95: Ashley Scott | H95: 10000 | J95: Action|Drama|Mystery|Sci-Fi | K95: Jensen Ackles | L95: Dark Angel | M95: 25329 | N95: 12051 | O95: John Savage | P95: 1 | Q95: cat burglar|female lead|future|mixed martial arts|post apocalypse | R95: http://www.imdb.com/title/tt0204993/?ref_=fn_tt_tt_1 | S95: 160 | T95: English | U95: USA | V95: TV-14 | Y95: 794 | Z95: 7.4 | AA95: 1.33 | AB95: 0
A96: Color | C96: 14 | D96: 60 | F96: 575 | G96: James Nesbitt | H96: 1000 | J96: Crime|Drama|Mystery | K96: Jason Flemyng | L96: The Missing | M96: 8739 | N96: 3537 | O96: Frances O'Connor | P96: 0 | Q96: france|journalist|limp|police detective|reporter | R96: http://www.imdb.com/title/tt3877200/?ref_=fn_tt_tt_1 | S96: 28 | T96: English | U96: UK | V96: Unrated | Y96: 773 | Z96: 8.1 | AB96: 0
A97: Color | C97: 17 | D97: 60 | F97: 84 | G97: Steve Gonsalves | H97: 155 | J97: Documentary | K97: Amy Bruni | L97: Ghost Hunters | M97: 5563 | N97: 552 | O97: Jason Hawes | P97: 0 | Q97: ghost|paranormal|paranormal research|shaky cam | R97: http://www.imdb.com/title/tt0426697/?ref_=fn_tt_tt_1 | S97: 57 | T97: English | U97: USA | V97: Unrated | Y97: 130 | Z97: 6.6 | AB97: 373
A98: Color | C98: 18 | D98: 60 | F98: 186 | G98: Nicole de Boer | H98: 443 | J98: Drama|Fantasy|Mystery|Sci-Fi | K98: David Ogden Stiers | L98: The Dead Zone | M98: 7122 | N98: 981 | O98: Chris Bruno | P98: 1 | Q98: psychic|psychic power|psychometry|spin off|supernatural power | R98: http://www.imdb.com/title/tt0281432/?ref_=fn_tt_tt_1 | S98: 77 | T98: English | U98: Canada | V98: TV-14 | Y98: 319 | Z98: 7.5 | AB98: 576
A99: Color | C99: 18 | D99: 60 | F99: 648 | G99: Joseph Gilgun | H99: 3000 | J99: Adventure|Drama|Fantasy|Mystery | K99: Dominic Cooper | L99: Preacher | M99: 22848 | N99: 6034 | O99: Ruth Negga | P99: 0 | Q99: heaven and hell|preacher|supernatural|vampire|vertigo comics | R99: http://www.imdb.com/title/tt5016504/?ref_=fn_tt_tt_1 | S99: 85 | T99: English | U99: Unknown | V99: TV-MA | Y99: 788 | Z99: 8.3 | AA99: 1.78 | AB99: 18000
A100: Color | C100: 20 | D100: 60 | F100: 543 | G100: Colin Ferguson | H100: 780 | J100: Comedy|Drama|Sci-Fi | K100: Joe Morton | L100: Eureka | M100: 39559 | N100: 4280 | O100: Salli Richardson-Whitfield | P100: 2 | Q100: alternate reality|pacific northwest|small town|small town life|small town sheriff | R100: http://www.imdb.com/title/tt0796264/?ref_=fn_tt_tt_1 | S100: 136 | T100: English | U100: USA | V100: TV-14 | Y100: 747 | Z100: 7.9 | AA100: 1.78 | AB100: 3000
...

Sheet Cleaning_Sheet
A1: Step No. | B1: Column(s) Affected | C1: Issue Identified | D1: Action Taken
A2: 1 | B2: All Columns | C2: 45 duplicate rows | D2: Removed using Excel’s “Remove Duplicates” feature
A3: 2 | B3: budget, gross | C3: 5 rows had both values missing | D3: Deleted these rows, as they were unusable for financial analysis
A4: 3 | B4: color | C4: 14 rows were blank | D4: Filled with "Color" as it’s the dominant value in the dataset
A5: 4 | B5: gross, color | C5: 12 rows had both color & gross missing | D5: Filled color as "Color"; retained rows for other non-financial tasks
A6: 5 | B6: director_name | C6: 101 rows missing director names | D6: Retained for other tasks; excluded from Director Analysis (Task D)
A7: 6 | B7: num_critic_for_reviews | C7: 47 blank rows | D7: Filled with median value = 110 to preserve data distribution
A8: 7 | B8: duration | C8: 14 blank rows | D8: Filled with median value = 103 minutes
A9: 8 | B9: director_facebook_likes | C9: 101 blanks (same rows as director_name) | D9: Retained as-is; excluded from analysis
A10: 9 | B10: actor_3_facebook_likes | C10: 21 blank rows | D10: Filled with column median
A11: 10 | B11: actor_2_name | C11: 12 blank rows | D11: Retained — names not safely assumable
A12: 11 | B12: actor_1_facebook_likes | C12: 7 blank rows | D12: Filled with column median
A13: 12 | B13: gross | C13: 869 blank rows | D13: Retained as-is; excluded from profit and gross-based tasks
... A24: 23 | B24: aspect_ratio | C24: 51 incorrect values (4, 16) | D24: Replaced 4 with 1.33 and 16 with 1.78 as per standard aspect ratios

Sheet Genres-imdb_Score
A1: genres | B1: imdb_score
A2: Animation|Comedy|Family | B2: 8.3
A3: Romance|Short | B3: 5.2
A4: Animation|Comedy | B4: 7.8
A5: Horror|Sci-Fi|Short|Thriller | B5: 6.2
A6: Documentary | B6: 6.8
A7: Comedy|Romance | B7: 7.3
A8: Comedy | B8: 8.1
A9: Animation|Comedy|Drama | B9: 8.2
A10: Comedy|Family|Fantasy | B10: 6.6
A11: Comedy|Romance | B11: 6.7
A12: Comedy | B12: 8.8
A13: Comedy|Family|Romance | B13: 6.1
... A4994: Crime|Drama|Thriller | B4994: 8.2

Sheet Genre_Cleaned
A1: genres | B1: imdb_score
A2: Animation | B2: 8.3
A3: Comedy | B3: 8.3
A4: Family | B4: 8.3
A5: Romance | B5: 5.2
A6: Short | B6: 5.2
A7: Animation | B7: 7.8
A8: Comedy | B8: 7.8
A9: Horror | B9: 6.2
A10: Sci-Fi | B10: 6.2
A11: Short | B11: 6.2
A12: Thriller | B12: 6.2
A13: Documentary | B13: 6.8
... A14372: Thriller | B14372: 8.2

Sheet Pivot - Movie Genre Analysis
A1: Geners | B1: Count of imdb_score | C1: Average of imdb_score | D1: Max of imdb_score | E1: Min of imdb_score | F1: StdDev of imdb_score | G1: Var of imdb_score | H1: Median of imdb_score | I1: Mode of imdb_score
A2: Action | B2: 1142 | C2: 6.2343257 | D2: 9.1 | E2: 1.7 | F2: 1.1106111 | G2: 1.233457 | H2: {=IFERROR(MEDIAN(IF(Cleaned_IMDB_Movies!J2:J4995=A2, Cleaned_IMDB_Movies!Z2:Z4995)), "")} -> 5.7 | I2: {=IFERROR(_xlfn.MODE.SNGL(IF(Cleaned_IMDB_Movies!J2:J4994=A2, Cleaned_IMDB_Movies!Z2:Z4994)), "")}
A3: Adventure | B3: 913 | C3: 6.4387733 | D3: 8.9 | E3: 1.9 | F3: 1.1273452 | G3: 1.2709073 | H3: {=IFERROR(MEDIAN(IF(Cleaned_IMDB_Movies!J3:J4996=A3, Cleaned_IMDB_Movies!Z3:Z4996)), "")} -> 7.2 | I3: {=IFERROR(_xlfn.MODE.SNGL(IF(Cleaned_IMDB_Movies!J3:J4995=A3, Cleaned_IMDB_Movies!Z3:Z4995)), "")}
A4: Animation | B4: 242 | C4: 6.5760331 | D4: 8.6 | E4: 1.7 | F4: 1.1395948 | G4: 1.2986763 | H4: {=IFERROR(MEDIAN(IF(Cleaned_IMDB_Movies!J4:J4997=A4, Cleaned_IMDB_Movies!Z4:Z4997)), "")} -> 4.25 | I4: {=IFERROR(_xlfn.MODE.SNGL(IF(Cleaned_IMDB_Movies!J4:J4996=A4, Cleaned_IMDB_Movies!Z4:Z4996)), "")}
A5: Biography | B5: 292 | C5: 7.15 | D5: 8.9 | E5: 4.5 | F5: 0.72375026 | G5: 0.52381443 | H5: {=IFERROR(MEDIAN(IF(Cleaned_IMDB_Movies!J5:J4998=A5, Cleaned_IMDB_Movies!Z5:Z4998)), "")} -> 5.7 | I5: {=IFERROR(_xlfn.MODE.SNGL(IF(Cleaned_IMDB_Movies!J5:J4997=A5, Cleaned_IMDB_Movies!Z5:Z4997)), "")}
A6: Comedy | B6: 1861 | C6: 6.1941429 | D6: 9.5 | E6: 1.7 | F6: 1.0890674 | G6: 1.1860678 | H6: {=IFERROR(MEDIAN(IF(Cleaned_IMDB_Movies!J6:J4999=A6, Cleaned_IMDB_Movies!Z6:Z4999)), "")} -> 5.9 | I6: {=IFERROR(_xlfn.MODE.SNGL(IF(Cleaned_IMDB_Movies!J6:J4998=A6, Cleaned_IMDB_Movies!Z6:Z4998)), "")} -> 6.5
A7: Crime | B7: 882 | C7: 6.55839 | D7: 9.3 | E7: 2.4 | F7: 1.0229505 | G7: 1.0464278 | H7: {=IFERROR(MEDIAN(IF(Cleaned_IMDB_Movies!J7:J5000=A7, Cleaned_IMDB_Movies!Z7:Z5000)), "")} | I7: {=IFERROR(_xlfn.MODE.SNGL(IF(Cleaned_IMDB_Movies!J7:J4999=A7, Cleaned_IMDB_Movies!Z7:Z4999)), "")}
A8: Documentary | B8: 120 | C8: 7.1808333 | D8: 8.7 | E8: 1.6 | F8: 1.0609411 | G8: 1.1255959 | H8: {=IFERROR(MEDIAN(IF(Cleaned_IMDB_Movies!J8:J5001=A8, Cleaned_IMDB_Movies!Z8:Z5001)), "")} -> 7.4 | I8: {=IFERROR(_xlfn.MODE.SNGL(IF(Cleaned_IMDB_Movies!J8:J5000=A8, Cleaned_IMDB_Movies!Z8:Z5000)), "")} -> 7.4
A9: Drama | B9: 2569 | C9: 6.7641495 | D9: 9.3 | E9: 2 | F9: 0.9530955 | G9: 0.90839103 | H9: {=IFERROR(MEDIAN(IF(Cleaned_IMDB_Movies!J9:J5002=A9, Cleaned_IMDB_Movies!Z9:Z5002)), "")} -> 7.1 | I9: {=IFERROR(_xlfn.MODE.SNGL(IF(Cleaned_IMDB_Movies!J9:J5001=A9, Cleaned_IMDB_Movies!Z9:Z5001)), "")} -> 7.3
A10: Family | B10: 544 | C10: 6.2474265 | D10: 8.7 | E10: 1.7 | F10: 1.2031086 | G10: 1.4474703 | H10: {=IFERROR(MEDIAN(IF(Cleaned_IMDB_Movies!J10:J5003=A10, Cleaned_IMDB_Movies!Z10:Z5003)), "")} -> 5.7 | I10: {=IFERROR(_xlfn.MODE.SNGL(IF(Cleaned_IMDB_Movies!J10:J5002=A10, Cleaned_IMDB_Movies!Z10:Z5002)), "")}
A11: Fantasy | B11: 604 | C11: 6.3110927 | D11: 8.9 | E11: 1.7 | F11: 1.1565486 | G11: 1.3376048 | H11: {=IFERROR(MEDIAN(IF(Cleaned_IMDB_Movies!J11:J5004=A11, Cleaned_IMDB_Movies!Z11:Z5004)), "")} -> 6.6 | I11: {=IFERROR(_xlfn.MODE.SNGL(IF(Cleaned_IMDB_Movies!J11:J5003=A11, Cleaned_IMDB_Movies!Z11:Z5003)), "")}
A12: Film-Noir | B12: 6 | C12: 7.6333333 | D12: 8.2 | E12: 7.1 | F12: 0.43204938 | G12: 0.18666667 | H12: {=IFERROR(MEDIAN(IF(Cleaned_IMDB_Movies!J12:J5005=A12, Cleaned_IMDB_Movies!Z12:Z5005)), "")} | I12: {=IFERROR(_xlfn.MODE.SNGL(IF(Cleaned_IMDB_Movies!J12:J5004=A12, Cleaned_IMDB_Movies!Z12:Z5004)), "")}
A13: Game-Show | B13: 1 | C13: 2.9 | D13: 2.9 | E13: 2.9 | F13: #DIV/0! | G13: #DIV/0! | H13: {=IFERROR(MEDIAN(IF(Cleaned_IMDB_Movies!J13:J5006=A13, Cleaned_IMDB_Movies!Z13:Z5006)), "")} | I13: {=IFERROR(_xlfn.MODE.SNGL(IF(Cleaned_IMDB_Movies!J13:J5005=A13, Cleaned_IMDB_Movies!Z13:Z5005)), "")}
A14: History | B14: 205 | C14: 7.084878 | D14: 8.9 | E14: 2 | F14: 0.88717198 | G14: 0.78707413 | H14: {=IFERROR(MEDIAN(IF(Cleaned_IMDB_Movies!J14:J5007=A14, Cleaned_IMDB_Movies!Z14:Z5007)), "")} -> 7.5 | I14: {=IFERROR(_xlfn.MODE.SNGL(IF(Cleaned_IMDB_Movies!J14:J5006=A14, Cleaned_IMDB_Movies!Z14:Z5006)), "")}
A15: Horror | B15: 555 | C15: 5.8351351 | D15: 8.7 | E15: 2.2 | F15: 1.1252796 | G15: 1.2662543 | H15: {=IFERROR(MEDIAN(IF(Cleaned_IMDB_Movies!J15:J5008=A15, Cleaned_IMDB_Movies!Z15:Z5008)), "")} -> 5.7 | I15: {=IFERROR(_xlfn.MODE.SNGL(IF(Cleaned_IMDB_Movies!J15:J5007=A15, Cleaned_IMDB_Movies!Z15:Z5007)), "")} -> 5.9
A16: Music | B16: 212 | C16: 6.4061321 | D16: 8.5 | E16: 1.6 | F16: 1.1831399 | G16: 1.39982 | H16: {=IFERROR(MEDIAN(IF(Cleaned_IMDB_Movies!J16:J5009=A16, Cleaned_IMDB_Movies!Z16:Z5009)), "")} -> 7.2 | I16: {=IFERROR(_xlfn.MODE.SNGL(IF(Cleaned_IMDB_Movies!J16:J5008=A16, Cleaned_IMDB_Movies!Z16:Z5008)), "")}
A17: Musical | B17: 132 | C17: 6.5075758 | D17: 8.5 | E17: 2.1 | F17: 1.2257181 | G17: 1.5023849 | H17: {=IFERROR(MEDIAN(IF(Cleaned_IMDB_Movies!J17:J5010=A17, Cleaned_IMDB_Movies!Z17:Z5010)), "")} -> 3.4 | I17: {=IFERROR(_xlfn.MODE.SNGL(IF(Cleaned_IMDB_Movies!J17:J5009=A17, Cleaned_IMDB_Movies!Z17:Z5009)), "")}
A18: Mystery | B18: 492 | C18: 6.4882114 | D18: 8.6 | E18: 2.2 | F18: 1.0823257 | G18: 1.171429 | H18: {=IFERROR(MEDIAN(IF(Cleaned_IMDB_Movies!J18:J5011=A18, Cleaned_IMDB_Movies!Z18:Z5011)), "")} | I18: {=IFERROR(_xlfn.MODE.SNGL(IF(Cleaned_IMDB_Movies!J18:J5010=A18, Cleaned_IMDB_Movies!Z18:Z5010)), "")}
A19: News | B19: 3 | C19: 7.5333333 | D19: 8.1 | E19: 7.1 | F19: 0.51316014 | G19: 0.26333333 | H19: {=IFERROR(MEDIAN(IF(Cleaned_IMDB_Movies!J19:J5012=A19, Cleaned_IMDB_Movies!Z19:Z5012)), "")} | I19: {=IFERROR(_xlfn.MODE.SNGL(IF(Cleaned_IMDB_Movies!J19:J5011=A19, Cleaned_IMDB_Movies!Z19:Z5011)), "")}
A20: Reality-TV | B20: 2 | C20: 4.75 | D20: 6.6 | E20: 2.9 | F20: 2.6162951 | G20: 6.845 | H20: {=IFERROR(MEDIAN(IF(Cleaned_IMDB_Movies!J20:J5013=A20, Cleaned_IMDB_Movies!Z20:Z5013)), "")} | I20: {=IFERROR(_xlfn.MODE.SNGL(IF(Cleaned_IMDB_Movies!J20:J5012=A20, Cleaned_IMDB_Movies!Z20:Z5012)), "")}
A21: Romance | B21: 1098 | C21: 6.4479053 | D21: 8.6 | E21: 2.1 | F21: 0.99779163 | G21: 0.99558813 | H21: {=IFERROR(MEDIAN(IF(Cleaned_IMDB_Movies!J21:J5014=A21, Cleaned_IMDB_Movies!Z21:Z5014)), "")} -> 5.65 | I21: {=IFERROR(_xlfn.MODE.SNGL(IF(Cleaned_IMDB_Movies!J21:J5013=A21, Cleaned_IMDB_Movies!Z21:Z5013)), "")} -> 5.1
A22: Sci-Fi | B22: 610 | C22: 6.2732787 | D22: 8.8 | E22: 1.9 | F22: 1.2039716 | G22: 1.4495475 | H22: {=IFERROR(MEDIAN(IF(Cleaned_IMDB_Movies!J22:J5015=A22, Cleaned_IMDB_Movies!Z22:Z5015)), "")} -> 5.2 | I22: {=IFERROR(_xlfn.MODE.SNGL(IF(Cleaned_IMDB_Movies!J22:J5014=A22, Cleaned_IMDB_Movies!Z22:Z5014)), "")}
A23: Short | B23: 5 | C23: 6.38 | D23: 7.1 | E23: 5.2 | F23: 0.74632433 | G23: 0.557 | H23: {=IFERROR(MEDIAN(IF(Cleaned_IMDB_Movies!J23:J5016=A23, Cleaned_IMDB_Movies!Z23:Z5016)), "")} | I23: {=IFERROR(_xlfn.MODE.SNGL(IF(Cleaned_IMDB_Movies!J23:J5015=A23, Cleaned_IMDB_Movies!Z23:Z5015)), "")}
A24: Sport | B24: 181 | C24: 6.6027624 | D24: 8.7 | E24: 2 | F24: 1.104105 | G24: 1.2190479 | H24: {=IFERROR(MEDIAN(IF(Cleaned_IMDB_Movies!J24:J5017=A24, Cleaned_IMDB_Movies!Z24:Z5017)), "")} | I24: {=IFERROR(_xlfn.MODE.SNGL(IF(Cleaned_IMDB_Movies!J24:J5016=A24, Cleaned_IMDB_Movies!Z24:Z5016)), "")}
A25: Thriller | B25: 1395 | C25: 6.3111111 | D25: 9 | E25: 2.2 | F25: 1.0502981 | G25: 1.1031261 | H25: {=IFERROR(MEDIAN(IF(Cleaned_IMDB_Movies!J25:J5018=A25, Cleaned_IMDB_Movies!Z25:Z5018)), "")} -> 5.4 | I25: {=IFERROR(_xlfn.MODE.SNGL(IF(Cleaned_IMDB_Movies!J25:J5017=A25, Cleaned_IMDB_Movies!Z25:Z5017)), "")} -> 3.9
... A27: Western | B27: 94 | C27: 6.7031915 | D27: 8.9 | E27: 3.8 | F27: 1.0557016 | G27: 1.1145058 | H27: {=IFERROR(MEDIAN(IF(Cleaned_IMDB_Movies!J27:J5020=A27, Cleaned_IMDB_Movies!Z27:Z5020)), "")} -> 7.05 | I27: {=IFERROR(_xlfn.MODE.SNGL(IF(Cleaned_IMDB_Movies!J27:J5019=A27, Cleaned_IMDB_Movies!Z27:Z5019)), "")} -> 7.1
A28: (blank) | H28: {=IFERROR(MEDIAN(IF(Cleaned_IMDB_Movies!J28:J5021=A28, Cleaned_IMDB_Movies!Z28:Z5021)), "")} | I28: {=IFERROR(_xlfn.MODE.SNGL(IF(Cleaned_IMDB_Movies!J28:J5020=A28, Cleaned_IMDB_Movies!Z28:Z5020)), "")}
A29: Grand Total | B29: 14371 | C29: 6.4490919 | D29: 9.5 | E29: 1.6 | F29: 1.0973092 | G29: 1.2040874 | H29: {=IFERROR(MEDIAN(IF(Cleaned_IMDB_Movies!J29:J5022=A29, Cleaned_IMDB_Movies!Z29:Z5022)), "")} | I29: {=IFERROR(_xlfn.MODE.SNGL(IF(Cleaned_IMDB_Movies!J29:J5021=A29, Cleaned_IMDB_Movies!Z29:Z5021)), "")}

Sheet Duration_Analysis 
A1: Movie Duration vs IMDb Score
A2: duration | B2: imdb_score
A3: 7 | B3: 8.3
A4: 7 | B4: 5.2
A5: 11 | B5: 7.8 | D5: Avg_duration | E5: Median_duration | F5: Standard Deviation
A6: 14 | B6: 6.2 | D6: =AVERAGE(A3:A4995) -> 107.24134 | E6: =MEDIAN(A3:A4995) -> 103 | F6: =_xlfn.STDEV.S(A3:A4995) -> 25.174774
A7: 20 | B7: 6.8
A8: 22 | B8: 7.3
A9: 22 | B9: 8.1
A10: 22 | B10: 8.2
A11: 22 | B11: 6.6
A12: 22 | B12: 6.7
A13: 22 | B13: 8.8
A14: 23 | B14: 6.1
A15: 23 | B15: 7.9
A16: 24 | B16: 7.9
A17: 24 | B17: 7
A18: 25 | B18: 8.4
... A4995: 511 | B4995: 8.2

Sheet Language_analysis
A1: language | B1: Language_Count | C1: Avg_IMDB_per_lang | D1: Median_IMDB_per_Lang | E1: Standard Deviation
A2: Telugu | B2: =COUNTIF(Cleaned_IMDB_Movies!T49:T5041, A2) -> 1 | C2: =AVERAGEIFS(Cleaned_IMDB_Movies!Z49:Z5041, Cleaned_IMDB_Movies!T49:T5041,Table11[[#This Row],[language]]) -> 8.4 | D2: {=MEDIAN(IF(Cleaned_IMDB_Movies!T49:T5041=A2, Cleaned_IMDB_Movies!Z49:Z5041))} -> 8.4 | E2: {=_xlfn.STDEV.P(_xlfn._xlws.FILTER(Cleaned_IMDB_Movies!Z49:Z5041,[1]Cleaned_IMDB_Movies!T49:T5041 = Table11[[#This Row],[language]]))} -> 0
A3: Polish | B3: =COUNTIF(Cleaned_IMDB_Movies!T4:T4996, A3) -> 4 | C3: =AVERAGEIFS(Cleaned_IMDB_Movies!Z4:Z4996, Cleaned_IMDB_Movies!T4:T4996,Table11[[#This Row],[language]]) -> 8.25 | D3: {=MEDIAN(IF(Cleaned_IMDB_Movies!T4:T4996=A3, Cleaned_IMDB_Movies!Z4:Z4996))} -> 8.25 | E3: {=_xlfn.STDEV.P(_xlfn._xlws.FILTER(Cleaned_IMDB_Movies!Z4:Z4996,[1]Cleaned_IMDB_Movies!T4:T4996 = Table11[[#This Row],[language]]))} -> 0.85
A4: None | B4: =COUNTIF(Cleaned_IMDB_Movies!T30:T5022, A4) -> 2 | C4: =AVERAGEIFS(Cleaned_IMDB_Movies!Z30:Z5022, Cleaned_IMDB_Movies!T30:T5022,Table11[[#This Row],[language]]) -> 7.95 | D4: {=MEDIAN(IF(Cleaned_IMDB_Movies!T30:T5022=A4, Cleaned_IMDB_Movies!Z30:Z5022))} -> 7.95 | E4: {=_xlfn.STDEV.P(_xlfn._xlws.FILTER(Cleaned_IMDB_Movies!Z30:Z5022,[1]Cleaned_IMDB_Movies!T30:T5022 = Table11[[#This Row],[language]]))} -> 0.55
A5: Indonesian | B5: =COUNTIF(Cleaned_IMDB_Movies!T28:T5020, A5) -> 2 | C5: =AVERAGEIFS(Cleaned_IMDB_Movies!Z28:Z5020, Cleaned_IMDB_Movies!T28:T5020,Table11[[#This Row],[language]]) -> 7.9 | D5: {=MEDIAN(IF(Cleaned_IMDB_Movies!T28:T5020=A5, Cleaned_IMDB_Movies!Z28:Z5020))} -> 7.9 | E5: {=_xlfn.STDEV.P(_xlfn._xlws.FILTER(Cleaned_IMDB_Movies!Z28:Z5020,[1]Cleaned_IMDB_Movies!T28:T5020 = Table11[[#This Row],[language]]))} -> 0.3
A6: Maya | B6: =COUNTIF(Cleaned_IMDB_Movies!T46:T5038, A6) -> 1 | C6: =AVERAGEIFS(Cleaned_IMDB_Movies!Z46:Z5038, Cleaned_IMDB_Movies!T46:T5038,Table11[[#This Row],[language]]) -> 7.8 | D6: {=MEDIAN(IF(Cleaned_IMDB_Movies!T46:T5038=A6, Cleaned_IMDB_Movies!Z46:Z5038))} -> 7.8 | E6: {=_xlfn.STDEV.P(_xlfn._xlws.FILTER(Cleaned_IMDB_Movies!Z46:Z5038,[1]Cleaned_IMDB_Movies!T46:T5038 = Table11[[#This Row],[language]]))} -> 0
A7: Hebrew | B7: =COUNTIF(Cleaned_IMDB_Movies!T19:T5011, A7) -> 5 | C7: =AVERAGEIFS(Cleaned_IMDB_Movies!Z19:Z5011, Cleaned_IMDB_Movies!T19:T5011,Table11[[#This Row],[language]]) -> 7.58 | D7: {=MEDIAN(IF(Cleaned_IMDB_Movies!T19:T5011=A7, Cleaned_IMDB_Movies!Z19:Z5011))} -> 7.6 | E7: {=_xlfn.STDEV.P(_xlfn._xlws.FILTER(Cleaned_IMDB_Movies!Z19:Z5011,[1]Cleaned_IMDB_Movies!T19:T5011 = Table11[[#This Row],[language]]))} -> 0.29933259
A8: Persian | B8: =COUNTIF(Cleaned_IMDB_Movies!T21:T5013, A8) -> 4 | C8: =AVERAGEIFS(Cleaned_IMDB_Movies!Z21:Z5013, Cleaned_IMDB_Movies!T21:T5013,Table11[[#This Row],[language]]) -> 7.575 | D8: {=MEDIAN(IF(Cleaned_IMDB_Movies!T21:T5013=A8, Cleaned_IMDB_Movies!Z21:Z5013))} -> 7.95 | E8: {=_xlfn.STDEV.P(_xlfn._xlws.FILTER(Cleaned_IMDB_Movies!Z21:Z5013,[1]Cleaned_IMDB_Movies!T21:T5013 = Table11[[#This Row],[language]]))} -> 1.042533
A9: Icelandic | B9: =COUNTIF(Cleaned_IMDB_Movies!T16:T5008, A9) -> 2 | C9: =AVERAGEIFS(Cleaned_IMDB_Movies!Z16:Z5008, Cleaned_IMDB_Movies!T16:T5008,Table11[[#This Row],[language]]) -> 7.55 | D9: {=MEDIAN(IF(Cleaned_IMDB_Movies!T16:T5008=A9, Cleaned_IMDB_Movies!Z16:Z5008))} -> 7.55 | E9: {=_xlfn.STDEV.P(_xlfn._xlws.FILTER(Cleaned_IMDB_Movies!Z16:Z5008,[1]Cleaned_IMDB_Movies!T16:T5008 = Table11[[#This Row],[language]]))} -> 0.65
A10: Danish | B10: =COUNTIF(Cleaned_IMDB_Movies!T6:T4998, A10) -> 5 | C10: =AVERAGEIFS(Cleaned_IMDB_Movies!Z6:Z4998, Cleaned_IMDB_Movies!T6:T4998,Table11[[#This Row],[language]]) -> 7.5 | D10: {=MEDIAN(IF(Cleaned_IMDB_Movies!T6:T4998=A10, Cleaned_IMDB_Movies!Z6:Z4998))} -> 8.1 | E10: {=_xlfn.STDEV.P(_xlfn._xlws.FILTER(Cleaned_IMDB_Movies!Z6:Z4998,[1]Cleaned_IMDB_Movies!T6:T4998 = Table11[[#This Row],[language]]))} -> 0.96332757
A11: Dari | B11: =COUNTIF(Cleaned_IMDB_Movies!T18:T5010, A11) -> 2 | C11: =AVERAGEIFS(Cleaned_IMDB_Movies!Z18:Z5010, Cleaned_IMDB_Movies!T18:T5010,Table11[[#This Row],[language]]) -> 7.5 | D11: {=MEDIAN(IF(Cleaned_IMDB_Movies!T18:T5010=A11, Cleaned_IMDB_Movies!Z18:Z5010))} -> 7.5 | E11: {=_xlfn.STDEV.P(_xlfn._xlws.FILTER(Cleaned_IMDB_Movies!Z18:Z5010,[1]Cleaned_IMDB_Movies!T18:T5010 = Table11[[#This Row],[language]]))} -> 0.1
A12: Dzongkha | B12: =COUNTIF(Cleaned_IMDB_Movies!T36:T5028, A12) -> 1 | C12: =AVERAGEIFS(Cleaned_IMDB_Movies!Z36:Z5028, Cleaned_IMDB_Movies!T36:T5028,Table11[[#This Row],[language]]) -> 7.5 | D12: {=MEDIAN(IF(Cleaned_IMDB_Movies!T36:T5028=A12, Cleaned_IMDB_Movies!Z36:Z5028))} -> 7.5 | E12: {=_xlfn.STDEV.P(_xlfn._xlws.FILTER(Cleaned_IMDB_Movies!Z36:Z5028,[1]Cleaned_IMDB_Movies!T36:T5028 = Table11[[#This Row],[language]]))} -> 0
A13: Portuguese | B13: =COUNTIF(Cleaned_IMDB_Movies!T29:T5021, A13) -> 8 | C13: =AVERAGEIFS(Cleaned_IMDB_Movies!Z29:Z5021, Cleaned_IMDB_Movies!T29:T5021,Table11[[#This Row],[language]]) -> 7.4875 | D13: {=MEDIAN(IF(Cleaned_IMDB_Movies!T29:T5021=A13, Cleaned_IMDB_Movies!Z29:Z5021))} -> 7.7 | E13: {=_xlfn.STDEV.P(_xlfn._xlws.FILTER(Cleaned_IMDB_Movies!Z29:Z5021,[1]Cleaned_IMDB_Movies!T29:T5021 = Table11[[#This Row],[language]]))} -> 0.82679728
A14: Swedish | B14: =COUNTIF(Cleaned_IMDB_Movies!T20:T5012, A14) -> 5 | C14: =AVERAGEIFS(Cleaned_IMDB_Movies!Z20:Z5012, Cleaned_IMDB_Movies!T20:T5012,Table11[[#This Row],[language]]) -> 7.44 | D14: {=MEDIAN(IF(Cleaned_IMDB_Movies!T20:T5012=A14, Cleaned_IMDB_Movies!Z20:Z5012))} -> 7.6 | E14: {=_xlfn.STDEV.P(_xlfn._xlws.FILTER(Cleaned_IMDB_Movies!Z20:Z5012,[1]Cleaned_IMDB_Movies!T20:T5012 = Table11[[#This Row],[language]]))} -> 0.67705244
A15: Dutch | B15: =COUNTIF(Cleaned_IMDB_Movies!T27:T5019, A15) -> 4 | C15: =AVERAGEIFS(Cleaned_IMDB_Movies!Z27:Z5019, Cleaned_IMDB_Movies!T27:T5019,Table11[[#This Row],[language]]) -> 7.425 | D15: {=MEDIAN(IF(Cleaned_IMDB_Movies!T27:T5019=A15, Cleaned_IMDB_Movies!Z27:Z5019))} -> 7.45 | E15: {=_xlfn.STDEV.P(_xlfn._xlws.FILTER(Cleaned_IMDB_Movies!Z27:Z5019,[1]Cleaned_IMDB_Movies!T27:T5019 = Table11[[#This Row],[language]]))} -> 0.37666298
A16: Swahili | B16: =COUNTIF(Cleaned_IMDB_Movies!T9:T5001, A16) -> 1 | C16: =AVERAGEIFS(Cleaned_IMDB_Movies!Z9:Z5001, Cleaned_IMDB_Movies!T9:T5001,Table11[[#This Row],[language]]) -> 7.4 | D16: {=MEDIAN(IF(Cleaned_IMDB_Movies!T9:T5001=A16, Cleaned_IMDB_Movies!Z9:Z5001))} -> 7.4 | E16: {=_xlfn.STDEV.P(_xlfn._xlws.FILTER(Cleaned_IMDB_Movies!Z9:Z5001,[1]Cleaned_IMDB_Movies!T9:T5001 = Table11[[#This Row],[language]]))} -> 0
A17: Czech | B17: =COUNTIF(Cleaned_IMDB_Movies!T39:T5031, A17) -> 1 | C17: =AVERAGEIFS(Cleaned_IMDB_Movies!Z39:Z5031, Cleaned_IMDB_Movies!T39:T5031,Table11[[#This Row],[language]]) -> 7.4 | D17: {=MEDIAN(IF(Cleaned_IMDB_Movies!T39:T5031=A17, Cleaned_IMDB_Movies!Z39:Z5031))} -> 7.4 | E17: {=_xlfn.STDEV.P(_xlfn._xlws.FILTER(Cleaned_IMDB_Movies!Z39:Z5031,[1]Cleaned_IMDB_Movies!T39:T5031 = Table11[[#This Row],[language]]))} -> 0
A18: Vietnamese | B18: =COUNTIF(Cleaned_IMDB_Movies!T45:T5037, A18) -> 1 | C18: =AVERAGEIFS(Cleaned_IMDB_Movies!Z45:Z5037, Cleaned_IMDB_Movies!T45:T5037,Table11[[#This Row],[language]]) -> 7.4 | D18: {=MEDIAN(IF(Cleaned_IMDB_Movies!T45:T5037=A18, Cleaned_IMDB_Movies!Z45:Z5037))} -> 7.4 | E18: {=_xlfn.STDEV.P(_xlfn._xlws.FILTER(Cleaned_IMDB_Movies!Z45:Z5037,[1]Cleaned_IMDB_Movies!T45:T5037 = Table11[[#This Row],[language]]))} -> 0
A19: Korean | B19: =COUNTIF(Cleaned_IMDB_Movies!T33:T5025, A19) -> 8 | C19: =AVERAGEIFS(Cleaned_IMDB_Movies!Z33:Z5025, Cleaned_IMDB_Movies!T33:T5025,Table11[[#This Row],[language]]) -> 7.3875 | D19: {=MEDIAN(IF(Cleaned_IMDB_Movies!T33:T5025=A19, Cleaned_IMDB_Movies!Z33:Z5025))} -> 7.5 | E19: {=_xlfn.STDEV.P(_xlfn._xlws.FILTER(Cleaned_IMDB_Movies!Z33:Z5025,[1]Cleaned_IMDB_Movies!T33:T5025 = Table11[[#This Row],[language]]))} -> 0.77207108
A20: Arabic | B20: =COUNTIF(Cleaned_IMDB_Movies!T10:T5002, A20) -> 5 | C20: =AVERAGEIFS(Cleaned_IMDB_Movies!Z10:Z5002, Cleaned_IMDB_Movies!T10:T5002,Table11[[#This Row],[language]]) -> 7.38 | D20: {=MEDIAN(IF(Cleaned_IMDB_Movies!T10:T5002=A20, Cleaned_IMDB_Movies!Z10:Z5002))} -> 7.4 | E20: {=_xlfn.STDEV.P(_xlfn._xlws.FILTER(Cleaned_IMDB_Movies!Z10:Z5002,[1]Cleaned_IMDB_Movies!T10:T5002 = Table11[[#This Row],[language]]))} -> 0.7909488
A21: Japanese | B21: =COUNTIF(Cleaned_IMDB_Movies!T3:T4995, A21) -> 17 | C21: =AVERAGEIFS(Cleaned_IMDB_Movies!Z3:Z4995, Cleaned_IMDB_Movies!T3:T4995,Table11[[#This Row],[language]]) -> 7.3470588 | D21: {=MEDIAN(IF(Cleaned_IMDB_Movies!T3:T4995=A21, Cleaned_IMDB_Movies!Z3:Z4995))} -> 7.5 | E21: {=_xlfn.STDEV.P(_xlfn._xlws.FILTER(Cleaned_IMDB_Movies!Z3:Z4995,[1]Cleaned_IMDB_Movies!T3:T4995 = Table11[[#This Row],[language]]))} -> 0.97021383
A22: German | B22: =COUNTIF(Cleaned_IMDB_Movies!T14:T5006, A22) -> 19 | C22: =AVERAGEIFS(Cleaned_IMDB_Movies!Z14:Z5006, Cleaned_IMDB_Movies!T14:T5006,Table11[[#This Row],[language]]) -> 7.3421053 | D22: {=MEDIAN(IF(Cleaned_IMDB_Movies!T14:T5006=A22, Cleaned_IMDB_Movies!Z14:Z5006))} -> 7.6 | E22: {=_xlfn.STDEV.P(_xlfn._xlws.FILTER(Cleaned_IMDB_Movies!Z14:Z5006,[1]Cleaned_IMDB_Movies!T14:T5006 = Table11[[#This Row],[language]]))} -> 0.92867522
A23: Greek | B23: =COUNTIF(Cleaned_IMDB_Movies!T26:T5018, A23) -> 1 | C23: =AVERAGEIFS(Cleaned_IMDB_Movies!Z26:Z5018, Cleaned_IMDB_Movies!T26:T5018,Table11[[#This Row],[language]]) -> 7.3 | D23: {=MEDIAN(IF(Cleaned_IMDB_Movies!T26:T5018=A23, Cleaned_IMDB_Movies!Z26:Z5018))} -> 7.3 | E23: {=_xlfn.STDEV.P(_xlfn._xlws.FILTER(Cleaned_IMDB_Movies!Z26:Z5018,[1]Cleaned_IMDB_Movies!T26:T5018 = Table11[[#This Row],[language]]))} -> 0
A24: Mongolian | B24: =COUNTIF(Cleaned_IMDB_Movies!T41:T5033, A24) -> 1 | C24: =AVERAGEIFS(Cleaned_IMDB_Movies!Z41:Z5033, Cleaned_IMDB_Movies!T41:T5033,Table11[[#This Row],[language]]) -> 7.3 | D24: {=MEDIAN(IF(Cleaned_IMDB_Movies!T41:T5033=A24, Cleaned_IMDB_Movies!Z41:Z5033))} -> 7.3 | E24: {=_xlfn.STDEV.P(_xlfn._xlws.FILTER(Cleaned_IMDB_Movies!Z41:Z5033,[1]Cleaned_IMDB_Movies!T41:T5033 = Table11[[#This Row],[language]]))} -> 0
A25: Italian | B25: =COUNTIF(Cleaned_IMDB_Movies!T8:T5000, A25) -> 11 | C25: =AVERAGEIFS(Cleaned_IMDB_Movies!Z8:Z5000, Cleaned_IMDB_Movies!T8:T5000,Table11[[#This Row],[language]]) -> 7.2272727 | D25: {=MEDIAN(IF(Cleaned_IMDB_Movies!T8:T5000=A25, Cleaned_IMDB_Movies!Z8:Z5000))} -> 7.3 | E25: {=_xlfn.STDEV.P(_xlfn._xlws.FILTER(Cleaned_IMDB_Movies!Z8:Z5000,[1]Cleaned_IMDB_Movies!T8:T5000 = Table11[[#This Row],[language]]))} -> 1.1863549
A26: Romanian | B26: =COUNTIF(Cleaned_IMDB_Movies!T34:T5026, A26) -> 2 | C26: =AVERAGEIFS(Cleaned_IMDB_Movies!Z34:Z5026, Cleaned_IMDB_Movies!T34:T5026,Table11[[#This Row],[language]]) -> 7.2 | D26: {=MEDIAN(IF(Cleaned_IMDB_Movies!T34:T5026=A26, Cleaned_IMDB_Movies!Z34:Z5026))} -> 7.2 | E26: {=_xlfn.STDEV.P(_xlfn._xlws.FILTER(Cleaned_IMDB_Movies!Z34:Z5026,[1]Cleaned_IMDB_Movies!T34:T5026 = Table11[[#This Row],[language]]))} -> 0.7
A27: Norwegian | B27: =COUNTIF(Cleaned_IMDB_Movies!T22:T5014, A27) -> 4 | C27: =AVERAGEIFS(Cleaned_IMDB_Movies!Z22:Z5014, Cleaned_IMDB_Movies!T22:T5014,Table11[[#This Row],[language]]) -> 7.15 | D27: {=MEDIAN(IF(Cleaned_IMDB_Movies!T22:T5014=A27, Cleaned_IMDB_Movies!Z22:Z5014))} -> 7.3 | E27: {=_xlfn.STDEV.P(_xlfn._xlws.FILTER(Cleaned_IMDB_Movies!Z22:Z5014,[1]Cleaned_IMDB_Movies!T22:T5014 = Table11[[#This Row],[language]]))} -> 0.49749372
A28: Zulu | B28: =COUNTIF(Cleaned_IMDB_Movies!T25:T5017, A28) -> 2 | C28: =AVERAGEIFS(Cleaned_IMDB_Movies!Z25:Z5017, Cleaned_IMDB_Movies!T25:T5017,Table11[[#This Row],[language]]) -> 7.1 | D28: {=MEDIAN(IF(Cleaned_IMDB_Movies!T25:T5017=A28, Cleaned_IMDB_Movies!Z25:Z5017))} -> 7.1 | E28: {=_xlfn.STDEV.P(_xlfn._xlws.FILTER(Cleaned_IMDB_Movies!Z25:Z5017,[1]Cleaned_IMDB_Movies!T25:T5017 = Table11[[#This Row],[language]]))} -> 0.2
A29: Kannada | B29: =COUNTIF(Cleaned_IMDB_Movies!T31:T5023, A29) -> 1 | C29: =AVERAGEIFS(Cleaned_IMDB_Movies!Z31:Z5023, Cleaned_IMDB_Movies!T31:T5023,Table11[[#This Row],[language]]) -> 7.1 | D29: {=MEDIAN(IF(Cleaned_IMDB_Movies!T31:T5023=A29, Cleaned_IMDB_Movies!Z31:Z5023))} -> 7.1 | E29: {=_xlfn.STDEV.P(_xlfn._xlws.FILTER(Cleaned_IMDB_Movies!Z31:Z5023,[1]Cleaned_IMDB_Movies!T31:T5023 = Table11[[#This Row],[language]]))} -> 0
A30: Aramaic | B30: =COUNTIF(Cleaned_IMDB_Movies!T40:T5032, A30) -> 1 | C30: =AVERAGEIFS(Cleaned_IMDB_Movies!Z40:Z5032, Cleaned_IMDB_Movies!T40:T5032,Table11[[#This Row],[language]]) -> 7.1 | D30: {=MEDIAN(IF(Cleaned_IMDB_Movies!T40:T5032=A30, Cleaned_IMDB_Movies!Z40:Z5032))} -> 7.1 | E30: {=_xlfn.STDEV.P(_xlfn._xlws.FILTER(Cleaned_IMDB_Movies!Z40:Z5032,[1]Cleaned_IMDB_Movies!T40:T5032 = Table11[[#This Row],[language]]))} -> 0
A31: Hungarian | B31: =COUNTIF(Cleaned_IMDB_Movies!T44:T5036, A31) -> 1 | C31: =AVERAGEIFS(Cleaned_IMDB_Movies!Z44:Z5036, Cleaned_IMDB_Movies!T44:T5036,Table11[[#This Row],[language]]) -> 7.1 | D31: {=MEDIAN(IF(Cleaned_IMDB_Movies!T44:T5036=A31, Cleaned_IMDB_Movies!Z44:Z5036))} -> 7.1 | E31: {=_xlfn.STDEV.P(_xlfn._xlws.FILTER(Cleaned_IMDB_Movies!Z44:Z5036,[1]Cleaned_IMDB_Movies!T44:T5036 = Table11[[#This Row],[language]]))} -> 0
A32: French | B32: =COUNTIF(Cleaned_IMDB_Movies!T7:T4999, A32) -> 73 | C32: =AVERAGEIFS(Cleaned_IMDB_Movies!Z7:Z4999, Cleaned_IMDB_Movies!T7:T4999,Table11[[#This Row],[language]]) -> 7.0383562 | D32: {=MEDIAN(IF(Cleaned_IMDB_Movies!T7:T4999=A32, Cleaned_IMDB_Movies!Z7:Z4999))} -> 7.2 | E32: {=_xlfn.STDEV.P(_xlfn._xlws.FILTER(Cleaned_IMDB_Movies!Z7:Z4999,[1]Cleaned_IMDB_Movies!T7:T4999 = Table11[[#This Row],[language]]))} -> 0.72198929
A33: Urdu | B33: =COUNTIF(Cleaned_IMDB_Movies!T32:T5024, A33) -> 1 | C33: =AVERAGEIFS(Cleaned_IMDB_Movies!Z32:Z5024, Cleaned_IMDB_Movies!T32:T5024,Table11[[#This Row],[language]]) -> 7 | D33: {=MEDIAN(IF(Cleaned_IMDB_Movies!T32:T5024=A33, Cleaned_IMDB_Movies!Z32:Z5024))} -> 7 | E33: {=_xlfn.STDEV.P(_xlfn._xlws.FILTER(Cleaned_IMDB_Movies!Z32:Z5024,[1]Cleaned_IMDB_Movies!T32:T5024 = Table11[[#This Row],[language]]))} -> 0
A34: Cantonese | B34: =COUNTIF(Cleaned_IMDB_Movies!T12:T5004, A34) -> 11 | C34: =AVERAGEIFS(Cleaned_IMDB_Movies!Z12:Z5004, Cleaned_IMDB_Movies!T12:T5004,Table11[[#This Row],[language]]) -> 6.9545455 | D34: {=MEDIAN(IF(Cleaned_IMDB_Movies!T12:T5004=A34, Cleaned_IMDB_Movies!Z12:Z5004))} -> 7.2 | E34: {=_xlfn.STDEV.P(_xlfn._xlws.FILTER(Cleaned_IMDB_Movies!Z12:Z5004,[1]Cleaned_IMDB_Movies!T12:T5004 = Table11[[#This Row],[language]]))} -> 0.67198977
A35: Aboriginal | B35: =COUNTIF(Cleaned_IMDB_Movies!T24:T5016, A35) -> 2 | C35: =AVERAGEIFS(Cleaned_IMDB_Movies!Z24:Z5016, Cleaned_IMDB_Movies!T24:T5016,Table11[[#This Row],[language]]) -> 6.95 | D35: {=MEDIAN(IF(Cleaned_IMDB_Movies!T24:T5016=A35, Cleaned_IMDB_Movies!Z24:Z5016))} -> 6.95 | E35: {=_xlfn.STDEV.P(_xlfn._xlws.FILTER(Cleaned_IMDB_Movies!Z24:Z5016,[1]Cleaned_IMDB_Movies!T24:T5016 = Table11[[#This Row],[language]]))} -> 0.55
A36: Spanish | B36: =COUNTIF(Cleaned_IMDB_Movies!T11:T5003, A36) -> 40 | C36: =AVERAGEIFS(Cleaned_IMDB_Movies!Z11:Z5003, Cleaned_IMDB_Movies!T11:T5003,Table11[[#This Row],[language]]) -> 6.9375 | D36: {=MEDIAN(IF(Cleaned_IMDB_Movies!T11:T5003=A36, Cleaned_IMDB_Movies!Z11:Z5003))} -> 7.15 | E36: {=_xlfn.STDEV.P(_xlfn._xlws.FILTER(Cleaned_IMDB_Movies!Z11:Z5003,[1]Cleaned_IMDB_Movies!T11:T5003 = Table11[[#This Row],[language]]))} -> 0.84430075
A37: Unknown | B37: =COUNTIF(Cleaned_IMDB_Movies!T5:T4997, A37) -> 9 | C37: =AVERAGEIFS(Cleaned_IMDB_Movies!Z5:Z4997, Cleaned_IMDB_Movies!T5:T4997,Table11[[#This Row],[language]]) -> 6.8 | D37: {=MEDIAN(IF(Cleaned_IMDB_Movies!T5:T4997=A37, Cleaned_IMDB_Movies!Z5:Z4997))} -> 6.7 | E37: {=_xlfn.STDEV.P(_xlfn._xlws.FILTER(Cleaned_IMDB_Movies!Z5:Z4997,[1]Cleaned_IMDB_Movies!T5:T4997 = Table11[[#This Row],[language]]))} -> 1.3759845
A38: Mandarin | B38: =COUNTIF(Cleaned_IMDB_Movies!T15:T5007, A38) -> 24 | C38: =AVERAGEIFS(Cleaned_IMDB_Movies!Z15:Z5007, Cleaned_IMDB_Movies!T15:T5007,Table11[[#This Row],[language]]) -> 6.7875 | D38: {=MEDIAN(IF(Cleaned_IMDB_Movies!T15:T5007=A38, Cleaned_IMDB_Movies!Z15:Z5007))} -> 7.05 | E38: {=_xlfn.STDEV.P(_xlfn._xlws.FILTER(Cleaned_IMDB_Movies!Z15:Z5007,[1]Cleaned_IMDB_Movies!T15:T5007 = Table11[[#This Row],[language]]))} -> 1.0150174
A39: Filipino | B39: =COUNTIF(Cleaned_IMDB_Movies!T43:T5035, A39) -> 1 | C39: =AVERAGEIFS(Cleaned_IMDB_Movies!Z43:Z5035, Cleaned_IMDB_Movies!T43:T5035,Table11[[#This Row],[language]]) -> 6.7 | D39: {=MEDIAN(IF(Cleaned_IMDB_Movies!T43:T5035=A39, Cleaned_IMDB_Movies!Z43:Z5035))} -> 6.7 | E39: {=_xlfn.STDEV.P(_xlfn._xlws.FILTER(Cleaned_IMDB_Movies!Z43:Z5035,[1]Cleaned_IMDB_Movies!T43:T5035 = Table11[[#This Row],[language]]))} -> 0
A40: Thai | B40: =COUNTIF(Cleaned_IMDB_Movies!T37:T5029, A40) -> 3 | C40: =AVERAGEIFS(Cleaned_IMDB_Movies!Z37:Z5029, Cleaned_IMDB_Movies!T37:T5029,Table11[[#This Row],[language]]) -> 6.6333333 | D40: {=MEDIAN(IF(Cleaned_IMDB_Movies!T37:T5029=A40, Cleaned_IMDB_Movies!Z37:Z5029))} -> 6.6 | E40: {=_xlfn.STDEV.P(_xlfn._xlws.FILTER(Cleaned_IMDB_Movies!Z37:Z5029,[1]Cleaned_IMDB_Movies!T37:T5029 = Table11[[#This Row],[language]]))} -> 0.3681787
A41: Hindi | B41: =COUNTIF(Cleaned_IMDB_Movies!T23:T5015, A41) -> 28 | C41: =AVERAGEIFS(Cleaned_IMDB_Movies!Z23:Z5015, Cleaned_IMDB_Movies!T23:T5015,Table11[[#This Row],[language]]) -> 6.6321429 | D41: {=MEDIAN(IF(Cleaned_IMDB_Movies!T23:T5015=A41, Cleaned_IMDB_Movies!Z23:Z5015))} -> 6.95 | E41: {=_xlfn.STDEV.P(_xlfn._xlws.FILTER(Cleaned_IMDB_Movies!Z23:Z5015,[1]Cleaned_IMDB_Movies!T23:T5015 = Table11[[#This Row],[language]]))} -> 1.3737471
A42: Panjabi | B42: =COUNTIF(Cleaned_IMDB_Movies!T47:T5039, A42) -> 1 | C42: =AVERAGEIFS(Cleaned_IMDB_Movies!Z47:Z5039, Cleaned_IMDB_Movies!T47:T5039,Table11[[#This Row],[language]]) -> 6.6 | D42: {=MEDIAN(IF(Cleaned_IMDB_Movies!T47:T5039=A42, Cleaned_IMDB_Movies!Z47:Z5039))} -> 6.6 | E42: {=_xlfn.STDEV.P(_xlfn._xlws.FILTER(Cleaned_IMDB_Movies!Z47:Z5039,[1]Cleaned_IMDB_Movies!T47:T5039 = Table11[[#This Row],[language]]))} -> 0
A43: Slovenian | B43: =COUNTIF(Cleaned_IMDB_Movies!T17:T5009, A43) -> 1 | C43: =AVERAGEIFS(Cleaned_IMDB_Movies!Z17:Z5009, Cleaned_IMDB_Movies!T17:T5009,Table11[[#This Row],[language]]) -> 6.4 | D43: {=MEDIAN(IF(Cleaned_IMDB_Movies!T17:T5009=A43, Cleaned_IMDB_Movies!Z17:Z5009))} -> 6.4 | E43: {=_xlfn.STDEV.P(_xlfn._xlws.FILTER(Cleaned_IMDB_Movies!Z17:Z5009,[1]Cleaned_IMDB_Movies!T17:T5009 = Table11[[#This Row],[language]]))} -> 0
A44: English | B44: =COUNTIF(Cleaned_IMDB_Movies!T2:T4994, A44) -> 4660 | C44: =AVERAGEIFS(Cleaned_IMDB_Movies!Z2:Z4994, Cleaned_IMDB_Movies!T2:T4994,Table11[[#This Row],[language]]) -> 6.3972961 | D44: {=MEDIAN(IF(Cleaned_IMDB_Movies!T2:T4994=A44, Cleaned_IMDB_Movies!Z2:Z4994))} -> 6.5 | E44: {=_xlfn.STDEV.P(_xlfn._xlws.FILTER(Cleaned_IMDB_Movies!Z2:Z4994,[1]Cleaned_IMDB_Movies!T2:T4994 = Table11[[#This Row],[language]]))} -> 1.1203354
A45: Russian | B45: =COUNTIF(Cleaned_IMDB_Movies!T13:T5005, A45) -> 11 | C45: =AVERAGEIFS(Cleaned_IMDB_Movies!Z13:Z5005, Cleaned_IMDB_Movies!T13:T5005,Table11[[#This Row],[language]]) -> 6.3636364 | D45: {=MEDIAN(IF(Cleaned_IMDB_Movies!T13:T5005=A45, Cleaned_IMDB_Movies!Z13:Z5005))} -> 6.5 | E45: {=_xlfn.STDEV.P(_xlfn._xlws.FILTER(Cleaned_IMDB_Movies!Z13:Z5005,[1]Cleaned_IMDB_Movies!T13:T5005 = Table11[[#This Row],[language]]))} -> 1.3192785
A46: Kazakh | B46: =COUNTIF(Cleaned_IMDB_Movies!T38:T5030, A46) -> 1 | C46: =AVERAGEIFS(Cleaned_IMDB_Movies!Z38:Z5030, Cleaned_IMDB_Movies!T38:T5030,Table11[[#This Row],[language]]) -> 6 | D46: {=MEDIAN(IF(Cleaned_IMDB_Movies!T38:T5030=A46, Cleaned_IMDB_Movies!Z38:Z5030))} -> 6 | E46: {=_xlfn.STDEV.P(_xlfn._xlws.FILTER(Cleaned_IMDB_Movies!Z38:Z5030,[1]Cleaned_IMDB_Movies!T38:T5030 = Table11[[#This Row],[language]]))} -> 0
A47: Chinese | B47: =COUNTIF(Cleaned_IMDB_Movies!T35:T5027, A47) -> 3 | C47: =AVERAGEIFS(Cleaned_IMDB_Movies!Z35:Z5027, Cleaned_IMDB_Movies!T35:T5027,Table11[[#This Row],[language]]) -> 5.6666667 | D47: {=MEDIAN(IF(Cleaned_IMDB_Movies!T35:T5027=A47, Cleaned_IMDB_Movies!Z35:Z5027))} -> 5.7 | E47: {=_xlfn.STDEV.P(_xlfn._xlws.FILTER(Cleaned_IMDB_Movies!Z35:Z5027,[1]Cleaned_IMDB_Movies!T35:T5027 = Table11[[#This Row],[language]]))} -> 0.44969125
A48: Tamil | B48: =COUNTIF(Cleaned_IMDB_Movies!T48:T5040, A48) -> 1 | C48: =AVERAGEIFS(Cleaned_IMDB_Movies!Z48:Z5040, Cleaned_IMDB_Movies!T48:T5040,Table11[[#This Row],[language]]) -> 5.1 | D48: {=MEDIAN(IF(Cleaned_IMDB_Movies!T48:T5040=A48, Cleaned_IMDB_Movies!Z48:Z5040))} -> 5.1 | E48: {=_xlfn.STDEV.P(_xlfn._xlws.FILTER(Cleaned_IMDB_Movies!Z48:Z5040,[1]Cleaned_IMDB_Movies!T48:T5040 = Table11[[#This Row],[language]]))} -> 0
A49: Bosnian | B49: =COUNTIF(Cleaned_IMDB_Movies!T42:T5034, A49) -> 1 | C49: =AVERAGEIFS(Cleaned_IMDB_Movies!Z42:Z5034, Cleaned_IMDB_Movies!T42:T5034,Table11[[#This Row],[language]]) -> 4.3 | D49: {=MEDIAN(IF(Cleaned_IMDB_Movies!T42:T5034=A49, Cleaned_IMDB_Movies!Z42:Z5034))} -> 4.3 | E49: {=_xlfn.STDEV.P(_xlfn._xlws.FILTER(Cleaned_IMDB_Movies!Z42:Z5034,[1]Cleaned_IMDB_Movies!T42:T5034 = Table11[[#This Row],[language]]))} -> 0

Sheet Budget_Analysis
A1: movie_title | B1: gross | C1: budget | D1: Profit Margin | E1: Correlation | F1: max | G1: Movie_highest_profit_margin
A2: Marilyn Hotchkiss' Ballroom Dancing and Charm School | B2: 333658 | C2: 34000 | D2: =B2-C2 -> 299658 | E2: =CORREL(C2:C3858, B2:B3858) -> 0.10103348 | F2: =MAX(D2:D3858) -> 523505847 | G2: =INDEX(A2:A3858, MATCH(MAX(D2:D3858), D2:D3858, 0)) -> Avatar
A3: Evil Dead II | B3: 5923044 | C3: 3600000 | D3: =B3-C3 -> 2323044
A4: Sea Rex 3D: Journey to a Prehistoric World | B4: 4074023 | C4: 5000000 | D4: =B4-C4 -> -925977
A5: Dolphins and Whales 3D: Tribes of the Ocean | B5: 7518876 | C5: 6000000 | D5: =B5-C5 -> 1518876
A6: Flame and Citron | B6: 145109 | C6: 45000000 | D6: =B6-C6 -> -44854891
A7: Taxi to the Dark Side | B7: 274661 | C7: 1000000 | D7: =B7-C7 -> -725339
A8: Winnie the Pooh | B8: 26687172 | C8: 30000000 | D8: =B8-C8 -> -3312828
A9: Pink Narcissus | B9: 8231 | C9: 27000 | D9: =B9-C9 -> -18769
A10: Timecrimes | B10: 38108 | C10: 2600000 | D10: =B10-C10 -> -2561892
A11: Pooh's Heffalump Movie | B11: 18081626 | C11: 20000000 | D11: =B11-C11 -> -1918374
A12: Austin Powers: International Man of Mystery | B12: 53868030 | C12: 17000000 | D12: =B12-C12 -> 36868030
A13: The Land Before Time | B13: 48092846 | C13: 12500000 | D13: =B13-C13 -> 35592846
A14: Antarctic Edge: 70° South | B14: 4914 | C14: 150000 | D14: =B14-C14 -> -145086
... A3858: Blood In, Blood Out | B3858: 4496583 | C3858: 35000000 | D3858: =B3858-C3858 -> -30503417

Sheet Director_analysis
A3: Directors | B3: Average of imdb_score | C3: Percentile
A4: John Blanchard | B4: 9.5 | C4: =PERCENTILE(B4:B2400, 0.9) -> 7.5
A5: Sadyk Sher-Niyaz | B5: 8.7 | C5: =PERCENTILE(B5:B2401, 0.9) -> 7.5
A6: Mitchell Altieri | B6: 8.7 | C6: =PERCENTILE(B6:B2402, 0.9) -> 7.5
A7: Cary Bell | B7: 8.7 | C7: =PERCENTILE(B7:B2403, 0.9) -> 7.5
A8: Mike Mayhall | B8: 8.6 | C8: =PERCENTILE(B8:B2404, 0.9) -> 7.5
A9: Charles Chaplin | B9: 8.6 | C9: =PERCENTILE(B9:B2405, 0.9) -> 7.5
A10: Ron Fricke | B10: 8.5 | C10: =PERCENTILE(B10:B2406, 0.9) -> 7.5
A11: Raja Menon | B11: 8.5 | C11: =PERCENTILE(B11:B2407, 0.9) -> 7.5
A12: Majid Majidi | B12: 8.5 | C12: =PERCENTILE(B12:B2408, 0.9) -> 7.5
A13: Damien Chazelle | B13: 8.5 | C13: =PERCENTILE(B13:B2409, 0.9) -> 7.5
A14: Sergio Leone | B14: 8.475 | C14: =PERCENTILE(B14:B2410, 0.9) -> 7.5
A15: Christopher Nolan | B15: 8.425 | C15: =PERCENTILE(B15:B2411, 0.9) -> 7.5
... A220: J.A. Bayona | B220: 7.55 | C220: =PERCENTILE(B220:B2616, 0.9) -> 7.2
B221: 7.5445545 | C221: =PERCENTILE(B221:B2617, 0.9) -> 7.2
A222: Paul Thomas Anderson | B222: 7.5166667 | C222: =PERCENTILE(B222:B2618, 0.9) -> 7.2
A223: William H. Macy | B223: 7.5 | C223: =PERCENTILE(B223:B2619, 0.9) -> 7.2
A224: Tom Putnam | B224: 7.5 | C224: =PERCENTILE(B224:B2620, 0.9) -> 7.2
A225: Tate Taylor | B225: 7.5 | C225: =PERCENTILE(B225:B2621, 0.9) -> 7.2
A226: Steve Box | B226: 7.5 | C226: =PERCENTILE(B226:B2622, 0.9) -> 7.2
A227: Tony Bancroft | B227: 7.5 | C227: =PERCENTILE(B227:B2623, 0.9) -> 7.2
A228: Tay Garnett | B228: 7.5 | C228: =PERCENTILE(B228:B2624, 0.9) -> 7.2
A229: Timothy Hines | B229: 7.5 | C229: =PERCENTILE(B229:B2625, 0.9) -> 7.2
A230: Sean Penn | B230: 7.5 | C230: =PERCENTILE(B230:B2626, 0.9) -> 7.2
A231: Shimit Amin | B231: 7.5 | C231: =PERCENTILE(B231:B2627, 0.9) -> 7.2
A232: Norman Ferguson | B232: 7.5 | C232: =PERCENTILE(B232:B2628, 0.9) -> 7.2
A233: Paul Haggis | B233: 7.5 | C233: =PERCENTILE(B233:B2629, 0.9) -> 7.2
... A2400: Grand Total | B2400: 6.4406369 | C2400: =PERCENTILE(B2400:B4796, 0.9) -> 6.4406369
